{"nm":"Successfull","ddd":0,"h":326,"w":316,"meta":{"g":"@lottiefiles/toolkit-js 0.26.1"},"layers":[{"ty":4,"nm":"Tick Mark","sr":1,"st":107,"op":314,"ip":204,"hd":false,"ddd":0,"bm":0,"hasMask":false,"ao":0,"ks":{"a":{"a":0,"k":[0,0,0],"ix":1},"s":{"a":1,"k":[{"o":{"x":0.167,"y":0.167},"i":{"x":0.833,"y":0.833},"s":[0,0,100],"t":204},{"s":[100,100,100],"t":210}],"ix":6},"sk":{"a":0,"k":0},"p":{"a":0,"k":[158,163,0],"ix":2},"r":{"a":0,"k":0,"ix":10},"sa":{"a":0,"k":0},"o":{"a":0,"k":100,"ix":11}},"ef":[],"shapes":[{"ty":"gr","bm":0,"hd":false,"mn":"ADBE Vector Group","nm":"Shape 1","ix":1,"cix":2,"np":3,"it":[{"ty":"sh","bm":0,"hd":false,"mn":"ADBE Vector Shape - Group","nm":"Path 1","ix":1,"d":1,"ks":{"a":0,"k":{"c":false,"i":[[0,0],[0,0],[0,0]],"o":[[0,0],[0,0],[0,0]],"v":[[33.5,-23.5],[-10,18.625],[-33.25,-3.25]]},"ix":2}},{"ty":"st","bm":0,"hd":false,"mn":"ADBE Vector Graphic - Stroke","nm":"Stroke 1","lc":2,"lj":2,"ml":1,"o":{"a":0,"k":100,"ix":4},"w":{"a":0,"k":14,"ix":5},"c":{"a":0,"k":[0.0549,0.0863,0.0941],"ix":3}},{"ty":"tr","a":{"a":0,"k":[0,0],"ix":1},"s":{"a":0,"k":[100,100],"ix":3},"sk":{"a":0,"k":0,"ix":4},"p":{"a":0,"k":[0,0],"ix":2},"r":{"a":0,"k":0,"ix":6},"sa":{"a":0,"k":0,"ix":5},"o":{"a":0,"k":100,"ix":7}}]},{"ty":"tm","bm":0,"hd":false,"mn":"ADBE Vector Filter - Trim","nm":"Trim Paths 1","ix":2,"e":{"a":0,"k":100,"ix":2},"o":{"a":0,"k":0,"ix":3},"s":{"a":1,"k":[{"o":{"x":0.333,"y":0},"i":{"x":0.667,"y":1},"s":[100],"t":204},{"s":[0],"t":214}],"ix":1},"m":1}],"ind":1},{"ty":0,"nm":"Counter","sr":1,"st":0,"op":240,"ip":0,"hd":false,"ddd":0,"bm":0,"hasMask":false,"ao":0,"ks":{"a":{"a":0,"k":[85,29.5,0],"ix":1},"s":{"a":1,"k":[{"o":{"x":0.333,"y":0},"i":{"x":0.667,"y":1},"s":[100,100,100],"t":193},{"o":{"x":0.333,"y":0},"i":{"x":0.667,"y":1},"s":[110,110,100],"t":197},{"s":[0,0,100],"t":206}],"ix":6},"sk":{"a":0,"k":0},"p":{"a":0,"k":[158.5,163,0],"ix":2},"r":{"a":0,"k":0,"ix":10},"sa":{"a":0,"k":0},"o":{"a":0,"k":100,"ix":11}},"ef":[],"w":170,"h":59,"refId":"comp_0","ind":2},{"ty":4,"nm":"Loading Layer","sr":1,"st":0,"op":240,"ip":0,"hd":false,"ddd":0,"bm":0,"hasMask":false,"ao":0,"ks":{"a":{"a":0,"k":[0,0,0],"ix":1},"s":{"a":0,"k":[394.813,394.813,100],"ix":6},"sk":{"a":0,"k":0},"p":{"a":0,"k":[158,160,0],"ix":2},"r":{"a":0,"k":0,"ix":10},"sa":{"a":0,"k":0},"o":{"a":0,"k":100,"ix":11}},"ef":[],"shapes":[{"ty":"gr","bm":0,"hd":false,"mn":"ADBE Vector Group","nm":"Group 1","ix":1,"cix":2,"np":2,"it":[{"ty":"sh","bm":0,"hd":false,"mn":"ADBE Vector Shape - Group","nm":"Path 1","ix":1,"d":1,"ks":{"a":0,"k":{"c":true,"i":[[-19.857,0],[0,-19.857],[19.857,0],[0,19.857]],"o":[[19.857,0],[0,19.857],[-19.857,0],[0,-19.857]],"v":[[0,-35.955],[35.955,0],[0,35.955],[-35.955,0]]},"ix":2}},{"ty":"st","bm":0,"hd":false,"mn":"ADBE Vector Graphic - Stroke","nm":"Stroke 1","lc":2,"lj":2,"ml":1,"o":{"a":0,"k":100,"ix":4},"w":{"a":0,"k":3.09,"ix":5},"c":{"a":0,"k":[0.8,1,0],"ix":3}},{"ty":"tr","a":{"a":0,"k":[0,0],"ix":1},"s":{"a":0,"k":[100,100],"ix":3},"sk":{"a":0,"k":0,"ix":4},"p":{"a":0,"k":[0,0],"ix":2},"r":{"a":0,"k":0,"ix":6},"sa":{"a":0,"k":0,"ix":5},"o":{"a":0,"k":100,"ix":7}}]},{"ty":"tm","bm":0,"hd":false,"mn":"ADBE Vector Filter - Trim","nm":"Trim Paths 1","ix":2,"e":{"a":1,"k":[{"o":{"x":0.167,"y":0.167},"i":{"x":0.833,"y":0.833},"s":[0],"t":0},{"s":[100],"t":191}],"ix":2},"o":{"a":0,"k":0,"ix":3},"s":{"a":0,"k":0,"ix":1},"m":1}],"ind":3},{"ty":4,"nm":"Loading BG","sr":1,"st":0,"op":240,"ip":0,"hd":false,"ddd":0,"bm":0,"hasMask":false,"ao":0,"ks":{"a":{"a":0,"k":[0,0,0],"ix":1},"s":{"a":0,"k":[394.813,394.813,100],"ix":6},"sk":{"a":0,"k":0},"p":{"a":0,"k":[158.5,160,0],"ix":2},"r":{"a":0,"k":0,"ix":10},"sa":{"a":0,"k":0},"o":{"a":0,"k":16,"ix":11}},"ef":[],"shapes":[{"ty":"gr","bm":0,"hd":false,"mn":"ADBE Vector Group","nm":"Group 1","ix":1,"cix":2,"np":2,"it":[{"ty":"sh","bm":0,"hd":false,"mn":"ADBE Vector Shape - Group","nm":"Path 1","ix":1,"d":1,"ks":{"a":0,"k":{"c":true,"i":[[-19.857,0],[0,-19.857],[19.857,0],[0,19.857]],"o":[[19.857,0],[0,19.857],[-19.857,0],[0,-19.857]],"v":[[0,-35.955],[35.955,0],[0,35.955],[-35.955,0]]},"ix":2}},{"ty":"st","bm":0,"hd":false,"mn":"ADBE Vector Graphic - Stroke","nm":"Stroke 1","lc":1,"lj":1,"ml":4,"o":{"a":0,"k":100,"ix":4},"w":{"a":0,"k":3.09,"ix":5},"c":{"a":0,"k":[0.0549,0.0863,0.0941],"ix":3}},{"ty":"tr","a":{"a":0,"k":[0,0],"ix":1},"s":{"a":0,"k":[100,100],"ix":3},"sk":{"a":0,"k":0,"ix":4},"p":{"a":0,"k":[0,0],"ix":2},"r":{"a":0,"k":0,"ix":6},"sa":{"a":0,"k":0,"ix":5},"o":{"a":0,"k":100,"ix":7}}]}],"ind":4}],"v":"5.6.3","fr":30,"op":240,"ip":0,"fonts":{"list":[{"ascent":74.1989135742188,"fClass":"","fFamily":"Montserrat","fStyle":"Bold","fName":"Montserrat-Bold","fPath":"","fWeight":"","origin":0}]},"chars":[{"ch":"0","fFamily":"Montserrat","size":58,"style":"Bold","w":67.9,"data":{"shapes":[{"ty":"gr","bm":0,"hd":false,"mn":"ADBE Vector Group","nm":"0","ix":1,"cix":2,"np":5,"it":[{"ty":"sh","bm":0,"hd":false,"mn":"ADBE Vector Shape - Group","nm":"0","ix":1,"d":1,"ks":{"a":0,"k":{"c":true,"i":[[-17.322,0],[0,23.264],[17.422,0],[0,-23.264]],"o":[[17.422,0],[0,-23.264],[-17.322,0],[0,23.264]],"v":[[34.14,1.208],[64.352,-35.248],[34.14,-71.704],[3.928,-35.248]]},"ix":2}},{"ty":"sh","bm":0,"hd":false,"mn":"ADBE Vector Shape - Group","nm":"0","ix":2,"d":1,"ks":{"a":0,"k":{"c":true,"i":[[8.157,0],[0,16.013],[-8.057,0],[0,-16.013]],"o":[[-8.057,0],[0,-16.013],[8.157,0],[0,16.013]],"v":[[34.14,-12.589],[20.444,-35.248],[34.14,-57.907],[47.937,-35.248]]},"ix":2}}]}]}},{"ch":"%","fFamily":"Montserrat","size":58,"style":"Bold","w":75.2,"data":{"shapes":[{"ty":"gr","bm":0,"hd":false,"mn":"ADBE Vector Group","nm":"%","ix":1,"cix":2,"np":8,"it":[{"ty":"sh","bm":0,"hd":false,"mn":"ADBE Vector Shape - Group","nm":"%","ix":1,"d":1,"ks":{"a":0,"k":{"c":true,"i":[[-10.272,0],[0,11.984],[10.272,0],[0,-11.884]],"o":[[10.272,0],[0,-11.984],[-10.272,0],[0,11.884]],"v":[[20.242,-32.428],[37.665,-51.865],[20.242,-71.301],[2.719,-51.865]]},"ix":2}},{"ty":"sh","bm":0,"hd":false,"mn":"ADBE Vector Shape - Group","nm":"%","ix":2,"d":1,"ks":{"a":0,"k":{"c":true,"i":[[0,0],[0,0],[0,0],[0,0]],"o":[[0,0],[0,0],[0,0],[0,0]],"v":[[14.099,0],[26.083,0],[74.222,-70.496],[62.238,-70.496]]},"ix":2}},{"ty":"sh","bm":0,"hd":false,"mn":"ADBE Vector Shape - Group","nm":"%","ix":3,"d":1,"ks":{"a":0,"k":{"c":true,"i":[[4.431,0],[0,7.452],[-4.33,0],[0,-7.553]],"o":[[-4.33,0],[0,-7.452],[4.431,0],[0,7.553]],"v":[[20.242,-40.686],[12.891,-51.865],[20.242,-63.043],[27.594,-51.865]]},"ix":2}},{"ty":"sh","bm":0,"hd":false,"mn":"ADBE Vector Shape - Group","nm":"%","ix":4,"d":1,"ks":{"a":0,"k":{"c":true,"i":[[-10.172,0],[0,11.884],[10.272,0],[0,-11.884]],"o":[[10.272,0],[0,-11.884],[-10.172,0],[0,11.884]],"v":[[68.079,0.806],[85.602,-18.631],[68.079,-38.068],[50.656,-18.631]]},"ix":2}},{"ty":"sh","bm":0,"hd":false,"mn":"ADBE Vector Shape - Group","nm":"%","ix":5,"d":1,"ks":{"a":0,"k":{"c":true,"i":[[4.431,0],[0,7.553],[-4.33,0],[0,-7.452]],"o":[[-4.33,0],[0,-7.553],[4.431,0],[0,7.452]],"v":[[68.079,-7.452],[60.727,-18.631],[68.079,-29.81],[75.43,-18.631]]},"ix":2}}]}]}},{"ch":"1","fFamily":"Montserrat","size":58,"style":"Bold","w":39.2,"data":{"shapes":[{"ty":"gr","bm":0,"hd":false,"mn":"ADBE Vector Group","nm":"1","ix":1,"cix":2,"np":3,"it":[{"ty":"sh","bm":0,"hd":false,"mn":"ADBE Vector Shape - Group","nm":"1","ix":1,"d":1,"ks":{"a":0,"k":{"c":true,"i":[[0,0],[0,0],[0,0],[0,0],[0,0],[0,0]],"o":[[0,0],[0,0],[0,0],[0,0],[0,0],[0,0]],"v":[[0.705,-70.496],[0.705,-57.404],[14.804,-57.404],[14.804,0],[31.119,0],[31.119,-70.496]]},"ix":2}}]}]}},{"ch":"2","fFamily":"Montserrat","size":58,"style":"Bold","w":59,"data":{"shapes":[{"ty":"gr","bm":0,"hd":false,"mn":"ADBE Vector Group","nm":"2","ix":1,"cix":2,"np":3,"it":[{"ty":"sh","bm":0,"hd":false,"mn":"ADBE Vector Shape - Group","nm":"2","ix":1,"d":1,"ks":{"a":0,"k":{"c":true,"i":[[0,0],[0,0],[0,6.848],[15.71,0],[5.438,-7.956],[0,0],[-6.042,0],[0,-5.539],[6.244,-5.942],[0,0],[0,0],[0,0],[0,0]],"o":[[0,0],[9.869,-9.164],[0,-12.79],[-12.689,0],[0,0],[3.424,-4.733],[7.452,0],[0,3.424],[0,0],[0,0],[0,0],[0,0],[0,0]],"v":[[26.285,-13.293],[42.499,-28.601],[54.282,-50.858],[28.098,-71.704],[0.101,-58.612],[11.984,-50.958],[26.587,-58.008],[37.866,-49.246],[30.515,-36.255],[3.323,-10.574],[3.323,0],[56.598,0],[56.598,-13.293]]},"ix":2}}]}]}},{"ch":"3","fFamily":"Montserrat","size":58,"style":"Bold","w":58.7,"data":{"shapes":[{"ty":"gr","bm":0,"hd":false,"mn":"ADBE Vector Group","nm":"3","ix":1,"cix":2,"np":3,"it":[{"ty":"sh","bm":0,"hd":false,"mn":"ADBE Vector Shape - Group","nm":"3","ix":1,"d":1,"ks":{"a":0,"k":{"c":true,"i":[[12.689,2.014],[0,0],[0,0],[0,0],[0,0],[0,0],[0,0],[0,0],[0,0],[0,-5.338],[8.157,0],[5.338,4.028],[0,0],[-9.869,0],[0,11.884]],"o":[[0,0],[0,0],[0,0],[0,0],[0,0],[0,0],[0,0],[0,0],[9.265,0],[0,5.74],[-7.352,0],[0,0],[6.848,4.834],[20.041,0],[0,-10.373]],"v":[[36.859,-41.794],[52.771,-59.921],[52.771,-70.496],[3.424,-70.496],[3.424,-57.404],[33.435,-57.404],[18.933,-40.988],[18.933,-30.212],[26.385,-30.212],[39.578,-21.552],[26.385,-12.488],[6.244,-18.832],[-0.101,-6.345],[26.788,1.208],[55.994,-21.552]]},"ix":2}}]}]}},{"ch":"4","fFamily":"Montserrat","size":58,"style":"Bold","w":68.9,"data":{"shapes":[{"ty":"gr","bm":0,"hd":false,"mn":"ADBE Vector Group","nm":"4","ix":1,"cix":2,"np":3,"it":[{"ty":"sh","bm":0,"hd":false,"mn":"ADBE Vector Shape - Group","nm":"4","ix":1,"d":1,"ks":{"a":0,"k":{"c":true,"i":[[0,0],[0,0],[0,0],[0,0],[0,0],[0,0],[0,0],[0,0],[0,0],[0,0],[0,0],[0,0],[0,0],[0,0],[0,0]],"o":[[0,0],[0,0],[0,0],[0,0],[0,0],[0,0],[0,0],[0,0],[0,0],[0,0],[0,0],[0,0],[0,0],[0,0],[0,0]],"v":[[68.481,-28.098],[57.001,-28.098],[57.001,-41.29],[41.592,-41.29],[41.592,-28.098],[22.659,-28.098],[53.476,-70.496],[36.356,-70.496],[3.122,-25.781],[3.122,-14.804],[41.089,-14.804],[41.089,0],[57.001,0],[57.001,-14.804],[68.481,-14.804]]},"ix":2}}]}]}},{"ch":"5","fFamily":"Montserrat","size":58,"style":"Bold","w":59,"data":{"shapes":[{"ty":"gr","bm":0,"hd":false,"mn":"ADBE Vector Group","nm":"5","ix":1,"cix":2,"np":3,"it":[{"ty":"sh","bm":0,"hd":false,"mn":"ADBE Vector Shape - Group","nm":"5","ix":1,"d":1,"ks":{"a":0,"k":{"c":true,"i":[[20.847,0],[0,0],[0,0],[0,0],[0,0],[0,0],[0,0],[0,0],[0,-5.539],[8.157,0],[5.338,4.028],[0,0],[-9.769,0],[0,12.488]],"o":[[0,0],[0,0],[0,0],[0,0],[0,0],[0,0],[0,0],[12.79,0],[0,5.74],[-7.352,0],[0,0],[6.848,4.834],[20.142,0],[0,-12.488]],"v":[[28.098,-44.009],[22.357,-44.009],[23.465,-57.404],[52.872,-57.404],[52.872,-70.496],[9.869,-70.496],[6.244,-30.817],[24.271,-30.817],[40.686,-21.652],[27.493,-12.488],[7.452,-18.832],[1.007,-6.345],[27.896,1.208],[57.202,-22.156]]},"ix":2}}]}]}},{"ch":"6","fFamily":"Montserrat","size":58,"style":"Bold","w":63.7,"data":{"shapes":[{"ty":"gr","bm":0,"hd":false,"mn":"ADBE Vector Group","nm":"6","ix":1,"cix":2,"np":5,"it":[{"ty":"sh","bm":0,"hd":false,"mn":"ADBE Vector Shape - Group","nm":"6","ix":1,"d":1,"ks":{"a":0,"k":{"c":true,"i":[[13.596,0],[4.129,-4.129],[-11.783,0],[-3.928,-2.618],[0,0],[7.452,0],[0,-24.371],[-19.437,0],[0,14.401]],"o":[[-7.352,0],[0.504,-13.495],[4.733,0],[0,0],[-4.935,-3.122],[-21.249,0],[0,22.76],[14.905,0],[0,-13.293]],"v":[[37.866,-44.211],[20.444,-37.967],[40.283,-58.411],[53.476,-54.886],[59.518,-66.87],[39.88,-71.704],[3.928,-33.737],[35.449,1.208],[62.137,-22.256]]},"ix":2}},{"ty":"sh","bm":0,"hd":false,"mn":"ADBE Vector Shape - Group","nm":"6","ix":2,"d":1,"ks":{"a":0,"k":{"c":true,"i":[[6.949,0],[0,6.042],[-7.15,0],[0,-6.445]],"o":[[-7.855,0],[0,-6.143],[7.251,0],[0,6.445]],"v":[[34.543,-10.977],[22.156,-21.451],[34.341,-32.025],[46.326,-21.451]]},"ix":2}}]}]}},{"ch":"7","fFamily":"Montserrat","size":58,"style":"Bold","w":62,"data":{"shapes":[{"ty":"gr","bm":0,"hd":false,"mn":"ADBE Vector Group","nm":"7","ix":1,"cix":2,"np":3,"it":[{"ty":"sh","bm":0,"hd":false,"mn":"ADBE Vector Shape - Group","nm":"7","ix":1,"d":1,"ks":{"a":0,"k":{"c":true,"i":[[0,0],[0,0],[0,0],[0,0],[0,0],[0,0],[0,0],[0,0],[0,0]],"o":[[0,0],[0,0],[0,0],[0,0],[0,0],[0,0],[0,0],[0,0],[0,0]],"v":[[2.618,-70.496],[2.618,-45.721],[17.12,-45.721],[17.12,-57.202],[40.485,-57.202],[15.207,0],[32.932,0],[59.116,-59.921],[59.116,-70.496]]},"ix":2}}]}]}},{"ch":"8","fFamily":"Montserrat","size":58,"style":"Bold","w":66,"data":{"shapes":[{"ty":"gr","bm":0,"hd":false,"mn":"ADBE Vector Group","nm":"8","ix":1,"cix":2,"np":6,"it":[{"ty":"sh","bm":0,"hd":false,"mn":"ADBE Vector Shape - Group","nm":"8","ix":1,"d":1,"ks":{"a":0,"k":{"c":true,"i":[[6.848,3.424],[0,6.345],[16.214,0],[0,-12.387],[-5.237,-3.223],[0,-7.553],[-17.825,0],[0,13.293]],"o":[[5.237,-3.223],[0,-12.387],[-16.013,0],[0,6.345],[-6.747,3.424],[0,13.293],[17.926,0],[0,-7.553]],"v":[[52.167,-37.061],[60.425,-51.563],[33.133,-71.704],[6.042,-51.563],[14.2,-37.061],[3.525,-20.444],[33.133,1.208],[62.943,-20.444]]},"ix":2}},{"ty":"sh","bm":0,"hd":false,"mn":"ADBE Vector Shape - Group","nm":"8","ix":2,"d":1,"ks":{"a":0,"k":{"c":true,"i":[[-6.546,0],[0,-5.539],[6.747,0],[0,5.338]],"o":[[6.647,0],[0,5.338],[-6.647,0],[0,-5.539]],"v":[[33.133,-59.72],[44.211,-50.858],[33.133,-42.197],[22.256,-50.858]]},"ix":2}},{"ty":"sh","bm":0,"hd":false,"mn":"ADBE Vector Shape - Group","nm":"8","ix":3,"d":1,"ks":{"a":0,"k":{"c":true,"i":[[8.157,0],[0,6.244],[-8.057,0],[0,-6.244]],"o":[[-8.057,0],[0,-6.244],[8.157,0],[0,6.244]],"v":[[33.133,-10.776],[20.041,-20.947],[33.133,-31.018],[46.426,-20.947]]},"ix":2}}]}]}},{"ch":"9","fFamily":"Montserrat","size":58,"style":"Bold","w":63.7,"data":{"shapes":[{"ty":"gr","bm":0,"hd":false,"mn":"ADBE Vector Group","nm":"9","ix":1,"cix":2,"np":5,"it":[{"ty":"sh","bm":0,"hd":false,"mn":"ADBE Vector Shape - Group","nm":"9","ix":1,"d":1,"ks":{"a":0,"k":{"c":true,"i":[[19.537,0],[0,-14.401],[-13.596,0],[-4.129,4.129],[11.682,0],[3.827,2.618],[0,0],[-7.452,0],[0,24.371]],"o":[[-14.905,0],[0,13.293],[7.352,0],[-0.504,13.596],[-4.834,0],[0,0],[4.935,3.122],[21.35,0],[0,-22.76]],"v":[[28.702,-71.704],[2.014,-48.239],[26.285,-26.285],[43.808,-32.629],[23.969,-12.085],[10.776,-15.61],[4.733,-3.625],[24.271,1.208],[60.223,-36.758]]},"ix":2}},{"ty":"sh","bm":0,"hd":false,"mn":"ADBE Vector Shape - Group","nm":"9","ix":2,"d":1,"ks":{"a":0,"k":{"c":true,"i":[[7.15,0],[0,6.445],[-6.949,0],[0,-6.042]],"o":[[-7.251,0],[0,-6.445],[7.755,0],[0,6.143]],"v":[[29.91,-38.47],[17.926,-49.045],[29.709,-59.518],[41.995,-49.045]]},"ix":2}}]}]}}],"assets":[{"nm":"","id":"comp_0","layers":[{"ty":5,"nm":"Loader Text 102","sr":1,"st":191,"op":253,"ip":191,"hd":false,"ddd":0,"bm":0,"hasMask":false,"ao":0,"ks":{"a":{"a":0,"k":[0,0,0],"ix":1},"s":{"a":0,"k":[100,100,100],"ix":6},"sk":{"a":0,"k":0},"p":{"a":0,"k":[85,50,0],"ix":2},"r":{"a":0,"k":0,"ix":10},"sa":{"a":0,"k":0},"o":{"a":1,"k":[{"o":{"x":0.167,"y":0.167},"i":{"x":0.833,"y":0.833},"s":[100],"t":388},{"s":[0],"t":395}],"ix":11}},"ef":[],"t":{"m":{"a":{"a":0,"k":[0,0],"ix":2},"g":1},"p":{},"a":[],"d":{"k":[{"s":{"f":"Montserrat-Bold","s":58,"t":"100%","fc":[0.0549,0.0863,0.0941],"lh":69.6,"tr":0,"j":2,"ca":0},"t":0}]}},"ind":1},{"ty":5,"nm":"Loader Text 101","sr":1,"st":189,"op":191,"ip":189,"hd":false,"ddd":0,"bm":0,"hasMask":false,"ao":0,"ks":{"a":{"a":0,"k":[0,0,0],"ix":1},"s":{"a":0,"k":[100,100,100],"ix":6},"sk":{"a":0,"k":0},"p":{"a":0,"k":[85,50,0],"ix":2},"r":{"a":0,"k":0,"ix":10},"sa":{"a":0,"k":0},"o":{"a":1,"k":[{"o":{"x":0.167,"y":0.167},"i":{"x":0.833,"y":0.833},"s":[100],"t":386},{"s":[0],"t":393}],"ix":11}},"ef":[],"t":{"m":{"a":{"a":0,"k":[0,0],"ix":2},"g":1},"p":{},"a":[],"d":{"k":[{"s":{"f":"Montserrat-Bold","s":58,"t":"99%","fc":[0.0549,0.0863,0.0941],"lh":69.6,"tr":0,"j":2,"ca":0},"t":0}]}},"ind":2},{"ty":5,"nm":"Loader Text 100","sr":1,"st":187,"op":189,"ip":187,"hd":false,"ddd":0,"bm":0,"hasMask":false,"ao":0,"ks":{"a":{"a":0,"k":[0,0,0],"ix":1},"s":{"a":0,"k":[100,100,100],"ix":6},"sk":{"a":0,"k":0},"p":{"a":0,"k":[85,50,0],"ix":2},"r":{"a":0,"k":0,"ix":10},"sa":{"a":0,"k":0},"o":{"a":1,"k":[{"o":{"x":0.167,"y":0.167},"i":{"x":0.833,"y":0.833},"s":[100],"t":384},{"s":[0],"t":391}],"ix":11}},"ef":[],"t":{"m":{"a":{"a":0,"k":[0,0],"ix":2},"g":1},"p":{},"a":[],"d":{"k":[{"s":{"f":"Montserrat-Bold","s":58,"t":"98%","fc":[0.0549,0.0863,0.0941],"lh":69.6,"tr":0,"j":2,"ca":0},"t":0}]}},"ind":3},{"ty":5,"nm":"Loader Text 99","sr":1,"st":185,"op":187,"ip":185,"hd":false,"ddd":0,"bm":0,"hasMask":false,"ao":0,"ks":{"a":{"a":0,"k":[0,0,0],"ix":1},"s":{"a":0,"k":[100,100,100],"ix":6},"sk":{"a":0,"k":0},"p":{"a":0,"k":[85,50,0],"ix":2},"r":{"a":0,"k":0,"ix":10},"sa":{"a":0,"k":0},"o":{"a":1,"k":[{"o":{"x":0.167,"y":0.167},"i":{"x":0.833,"y":0.833},"s":[100],"t":382},{"s":[0],"t":389}],"ix":11}},"ef":[],"t":{"m":{"a":{"a":0,"k":[0,0],"ix":2},"g":1},"p":{},"a":[],"d":{"k":[{"s":{"f":"Montserrat-Bold","s":58,"t":"97%","fc":[0.0549,0.0863,0.0941],"lh":69.6,"tr":0,"j":2,"ca":0},"t":0}]}},"ind":4},{"ty":5,"nm":"Loader Text 98","sr":1,"st":183,"op":185,"ip":183,"hd":false,"ddd":0,"bm":0,"hasMask":false,"ao":0,"ks":{"a":{"a":0,"k":[0,0,0],"ix":1},"s":{"a":0,"k":[100,100,100],"ix":6},"sk":{"a":0,"k":0},"p":{"a":0,"k":[85,50,0],"ix":2},"r":{"a":0,"k":0,"ix":10},"sa":{"a":0,"k":0},"o":{"a":1,"k":[{"o":{"x":0.167,"y":0.167},"i":{"x":0.833,"y":0.833},"s":[100],"t":380},{"s":[0],"t":387}],"ix":11}},"ef":[],"t":{"m":{"a":{"a":0,"k":[0,0],"ix":2},"g":1},"p":{},"a":[],"d":{"k":[{"s":{"f":"Montserrat-Bold","s":58,"t":"96%","fc":[0.0549,0.0863,0.0941],"lh":69.6,"tr":0,"j":2,"ca":0},"t":0}]}},"ind":5},{"ty":5,"nm":"Loader Text 97","sr":1,"st":181,"op":183,"ip":181,"hd":false,"ddd":0,"bm":0,"hasMask":false,"ao":0,"ks":{"a":{"a":0,"k":[0,0,0],"ix":1},"s":{"a":0,"k":[100,100,100],"ix":6},"sk":{"a":0,"k":0},"p":{"a":0,"k":[85,50,0],"ix":2},"r":{"a":0,"k":0,"ix":10},"sa":{"a":0,"k":0},"o":{"a":1,"k":[{"o":{"x":0.167,"y":0.167},"i":{"x":0.833,"y":0.833},"s":[100],"t":378},{"s":[0],"t":385}],"ix":11}},"ef":[],"t":{"m":{"a":{"a":0,"k":[0,0],"ix":2},"g":1},"p":{},"a":[],"d":{"k":[{"s":{"f":"Montserrat-Bold","s":58,"t":"95%","fc":[0.0549,0.0863,0.0941],"lh":69.6,"tr":0,"j":2,"ca":0},"t":0}]}},"ind":6},{"ty":5,"nm":"Loader Text 96","sr":1,"st":179,"op":181,"ip":179,"hd":false,"ddd":0,"bm":0,"hasMask":false,"ao":0,"ks":{"a":{"a":0,"k":[0,0,0],"ix":1},"s":{"a":0,"k":[100,100,100],"ix":6},"sk":{"a":0,"k":0},"p":{"a":0,"k":[85,50,0],"ix":2},"r":{"a":0,"k":0,"ix":10},"sa":{"a":0,"k":0},"o":{"a":1,"k":[{"o":{"x":0.167,"y":0.167},"i":{"x":0.833,"y":0.833},"s":[100],"t":376},{"s":[0],"t":383}],"ix":11}},"ef":[],"t":{"m":{"a":{"a":0,"k":[0,0],"ix":2},"g":1},"p":{},"a":[],"d":{"k":[{"s":{"f":"Montserrat-Bold","s":58,"t":"94%","fc":[0.0549,0.0863,0.0941],"lh":69.6,"tr":0,"j":2,"ca":0},"t":0}]}},"ind":7},{"ty":5,"nm":"Loader Text 95","sr":1,"st":177,"op":179,"ip":177,"hd":false,"ddd":0,"bm":0,"hasMask":false,"ao":0,"ks":{"a":{"a":0,"k":[0,0,0],"ix":1},"s":{"a":0,"k":[100,100,100],"ix":6},"sk":{"a":0,"k":0},"p":{"a":0,"k":[85,50,0],"ix":2},"r":{"a":0,"k":0,"ix":10},"sa":{"a":0,"k":0},"o":{"a":1,"k":[{"o":{"x":0.167,"y":0.167},"i":{"x":0.833,"y":0.833},"s":[100],"t":374},{"s":[0],"t":381}],"ix":11}},"ef":[],"t":{"m":{"a":{"a":0,"k":[0,0],"ix":2},"g":1},"p":{},"a":[],"d":{"k":[{"s":{"f":"Montserrat-Bold","s":58,"t":"93%","fc":[0.0549,0.0863,0.0941],"lh":69.6,"tr":0,"j":2,"ca":0},"t":0}]}},"ind":8},{"ty":5,"nm":"Loader Text 94","sr":1,"st":175,"op":177,"ip":175,"hd":false,"ddd":0,"bm":0,"hasMask":false,"ao":0,"ks":{"a":{"a":0,"k":[0,0,0],"ix":1},"s":{"a":0,"k":[100,100,100],"ix":6},"sk":{"a":0,"k":0},"p":{"a":0,"k":[85,50,0],"ix":2},"r":{"a":0,"k":0,"ix":10},"sa":{"a":0,"k":0},"o":{"a":1,"k":[{"o":{"x":0.167,"y":0.167},"i":{"x":0.833,"y":0.833},"s":[100],"t":372},{"s":[0],"t":379}],"ix":11}},"ef":[],"t":{"m":{"a":{"a":0,"k":[0,0],"ix":2},"g":1},"p":{},"a":[],"d":{"k":[{"s":{"f":"Montserrat-Bold","s":58,"t":"92%","fc":[0.0549,0.0863,0.0941],"lh":69.6,"tr":0,"j":2,"ca":0},"t":0}]}},"ind":9},{"ty":5,"nm":"Loader Text 93","sr":1,"st":173,"op":175,"ip":173,"hd":false,"ddd":0,"bm":0,"hasMask":false,"ao":0,"ks":{"a":{"a":0,"k":[0,0,0],"ix":1},"s":{"a":0,"k":[100,100,100],"ix":6},"sk":{"a":0,"k":0},"p":{"a":0,"k":[85,50,0],"ix":2},"r":{"a":0,"k":0,"ix":10},"sa":{"a":0,"k":0},"o":{"a":1,"k":[{"o":{"x":0.167,"y":0.167},"i":{"x":0.833,"y":0.833},"s":[100],"t":370},{"s":[0],"t":377}],"ix":11}},"ef":[],"t":{"m":{"a":{"a":0,"k":[0,0],"ix":2},"g":1},"p":{},"a":[],"d":{"k":[{"s":{"f":"Montserrat-Bold","s":58,"t":"91%","fc":[0.0549,0.0863,0.0941],"lh":69.6,"tr":0,"j":2,"ca":0},"t":0}]}},"ind":10},{"ty":5,"nm":"Loader Text 92","sr":1,"st":171,"op":173,"ip":171,"hd":false,"ddd":0,"bm":0,"hasMask":false,"ao":0,"ks":{"a":{"a":0,"k":[0,0,0],"ix":1},"s":{"a":0,"k":[100,100,100],"ix":6},"sk":{"a":0,"k":0},"p":{"a":0,"k":[85,50,0],"ix":2},"r":{"a":0,"k":0,"ix":10},"sa":{"a":0,"k":0},"o":{"a":1,"k":[{"o":{"x":0.167,"y":0.167},"i":{"x":0.833,"y":0.833},"s":[100],"t":368},{"s":[0],"t":375}],"ix":11}},"ef":[],"t":{"m":{"a":{"a":0,"k":[0,0],"ix":2},"g":1},"p":{},"a":[],"d":{"k":[{"s":{"f":"Montserrat-Bold","s":58,"t":"90%","fc":[0.0549,0.0863,0.0941],"lh":69.6,"tr":0,"j":2,"ca":0},"t":0}]}},"ind":11},{"ty":5,"nm":"Loader Text 91","sr":1,"st":170,"op":171,"ip":170,"hd":false,"ddd":0,"bm":0,"hasMask":false,"ao":0,"ks":{"a":{"a":0,"k":[0,0,0],"ix":1},"s":{"a":0,"k":[100,100,100],"ix":6},"sk":{"a":0,"k":0},"p":{"a":0,"k":[85,50,0],"ix":2},"r":{"a":0,"k":0,"ix":10},"sa":{"a":0,"k":0},"o":{"a":1,"k":[{"o":{"x":0.167,"y":0.167},"i":{"x":0.833,"y":0.833},"s":[100],"t":367},{"s":[0],"t":374}],"ix":11}},"ef":[],"t":{"m":{"a":{"a":0,"k":[0,0],"ix":2},"g":1},"p":{},"a":[],"d":{"k":[{"s":{"f":"Montserrat-Bold","s":58,"t":"89%","fc":[0.0549,0.0863,0.0941],"lh":69.6,"tr":0,"j":2,"ca":0},"t":0}]}},"ind":12},{"ty":5,"nm":"Loader Text 90","sr":1,"st":168,"op":170,"ip":168,"hd":false,"ddd":0,"bm":0,"hasMask":false,"ao":0,"ks":{"a":{"a":0,"k":[0,0,0],"ix":1},"s":{"a":0,"k":[100,100,100],"ix":6},"sk":{"a":0,"k":0},"p":{"a":0,"k":[85,50,0],"ix":2},"r":{"a":0,"k":0,"ix":10},"sa":{"a":0,"k":0},"o":{"a":1,"k":[{"o":{"x":0.167,"y":0.167},"i":{"x":0.833,"y":0.833},"s":[100],"t":365},{"s":[0],"t":372}],"ix":11}},"ef":[],"t":{"m":{"a":{"a":0,"k":[0,0],"ix":2},"g":1},"p":{},"a":[],"d":{"k":[{"s":{"f":"Montserrat-Bold","s":58,"t":"88%","fc":[0.0549,0.0863,0.0941],"lh":69.6,"tr":0,"j":2,"ca":0},"t":0}]}},"ind":13},{"ty":5,"nm":"Loader Text 89","sr":1,"st":166,"op":168,"ip":166,"hd":false,"ddd":0,"bm":0,"hasMask":false,"ao":0,"ks":{"a":{"a":0,"k":[0,0,0],"ix":1},"s":{"a":0,"k":[100,100,100],"ix":6},"sk":{"a":0,"k":0},"p":{"a":0,"k":[85,50,0],"ix":2},"r":{"a":0,"k":0,"ix":10},"sa":{"a":0,"k":0},"o":{"a":1,"k":[{"o":{"x":0.167,"y":0.167},"i":{"x":0.833,"y":0.833},"s":[100],"t":363},{"s":[0],"t":370}],"ix":11}},"ef":[],"t":{"m":{"a":{"a":0,"k":[0,0],"ix":2},"g":1},"p":{},"a":[],"d":{"k":[{"s":{"f":"Montserrat-Bold","s":58,"t":"87%","fc":[0.0549,0.0863,0.0941],"lh":69.6,"tr":0,"j":2,"ca":0},"t":0}]}},"ind":14},{"ty":5,"nm":"Loader Text 88","sr":1,"st":164,"op":166,"ip":164,"hd":false,"ddd":0,"bm":0,"hasMask":false,"ao":0,"ks":{"a":{"a":0,"k":[0,0,0],"ix":1},"s":{"a":0,"k":[100,100,100],"ix":6},"sk":{"a":0,"k":0},"p":{"a":0,"k":[85,50,0],"ix":2},"r":{"a":0,"k":0,"ix":10},"sa":{"a":0,"k":0},"o":{"a":1,"k":[{"o":{"x":0.167,"y":0.167},"i":{"x":0.833,"y":0.833},"s":[100],"t":361},{"s":[0],"t":368}],"ix":11}},"ef":[],"t":{"m":{"a":{"a":0,"k":[0,0],"ix":2},"g":1},"p":{},"a":[],"d":{"k":[{"s":{"f":"Montserrat-Bold","s":58,"t":"86%","fc":[0.0549,0.0863,0.0941],"lh":69.6,"tr":0,"j":2,"ca":0},"t":0}]}},"ind":15},{"ty":5,"nm":"Loader Text 87","sr":1,"st":162,"op":164,"ip":162,"hd":false,"ddd":0,"bm":0,"hasMask":false,"ao":0,"ks":{"a":{"a":0,"k":[0,0,0],"ix":1},"s":{"a":0,"k":[100,100,100],"ix":6},"sk":{"a":0,"k":0},"p":{"a":0,"k":[85,50,0],"ix":2},"r":{"a":0,"k":0,"ix":10},"sa":{"a":0,"k":0},"o":{"a":1,"k":[{"o":{"x":0.167,"y":0.167},"i":{"x":0.833,"y":0.833},"s":[100],"t":359},{"s":[0],"t":366}],"ix":11}},"ef":[],"t":{"m":{"a":{"a":0,"k":[0,0],"ix":2},"g":1},"p":{},"a":[],"d":{"k":[{"s":{"f":"Montserrat-Bold","s":58,"t":"85%","fc":[0.0549,0.0863,0.0941],"lh":69.6,"tr":0,"j":2,"ca":0},"t":0}]}},"ind":16},{"ty":5,"nm":"Loader Text 86","sr":1,"st":160,"op":162,"ip":160,"hd":false,"ddd":0,"bm":0,"hasMask":false,"ao":0,"ks":{"a":{"a":0,"k":[0,0,0],"ix":1},"s":{"a":0,"k":[100,100,100],"ix":6},"sk":{"a":0,"k":0},"p":{"a":0,"k":[85,50,0],"ix":2},"r":{"a":0,"k":0,"ix":10},"sa":{"a":0,"k":0},"o":{"a":1,"k":[{"o":{"x":0.167,"y":0.167},"i":{"x":0.833,"y":0.833},"s":[100],"t":357},{"s":[0],"t":364}],"ix":11}},"ef":[],"t":{"m":{"a":{"a":0,"k":[0,0],"ix":2},"g":1},"p":{},"a":[],"d":{"k":[{"s":{"f":"Montserrat-Bold","s":58,"t":"84%","fc":[0.0549,0.0863,0.0941],"lh":69.6,"tr":0,"j":2,"ca":0},"t":0}]}},"ind":17},{"ty":5,"nm":"Loader Text 85","sr":1,"st":158,"op":160,"ip":158,"hd":false,"ddd":0,"bm":0,"hasMask":false,"ao":0,"ks":{"a":{"a":0,"k":[0,0,0],"ix":1},"s":{"a":0,"k":[100,100,100],"ix":6},"sk":{"a":0,"k":0},"p":{"a":0,"k":[85,50,0],"ix":2},"r":{"a":0,"k":0,"ix":10},"sa":{"a":0,"k":0},"o":{"a":1,"k":[{"o":{"x":0.167,"y":0.167},"i":{"x":0.833,"y":0.833},"s":[100],"t":355},{"s":[0],"t":362}],"ix":11}},"ef":[],"t":{"m":{"a":{"a":0,"k":[0,0],"ix":2},"g":1},"p":{},"a":[],"d":{"k":[{"s":{"f":"Montserrat-Bold","s":58,"t":"83%","fc":[0.0549,0.0863,0.0941],"lh":69.6,"tr":0,"j":2,"ca":0},"t":0}]}},"ind":18},{"ty":5,"nm":"Loader Text 84","sr":1,"st":156,"op":158,"ip":156,"hd":false,"ddd":0,"bm":0,"hasMask":false,"ao":0,"ks":{"a":{"a":0,"k":[0,0,0],"ix":1},"s":{"a":0,"k":[100,100,100],"ix":6},"sk":{"a":0,"k":0},"p":{"a":0,"k":[85,50,0],"ix":2},"r":{"a":0,"k":0,"ix":10},"sa":{"a":0,"k":0},"o":{"a":1,"k":[{"o":{"x":0.167,"y":0.167},"i":{"x":0.833,"y":0.833},"s":[100],"t":353},{"s":[0],"t":360}],"ix":11}},"ef":[],"t":{"m":{"a":{"a":0,"k":[0,0],"ix":2},"g":1},"p":{},"a":[],"d":{"k":[{"s":{"f":"Montserrat-Bold","s":58,"t":"82%","fc":[0.0549,0.0863,0.0941],"lh":69.6,"tr":0,"j":2,"ca":0},"t":0}]}},"ind":19},{"ty":5,"nm":"Loader Text 83","sr":1,"st":154,"op":156,"ip":154,"hd":false,"ddd":0,"bm":0,"hasMask":false,"ao":0,"ks":{"a":{"a":0,"k":[0,0,0],"ix":1},"s":{"a":0,"k":[100,100,100],"ix":6},"sk":{"a":0,"k":0},"p":{"a":0,"k":[85,50,0],"ix":2},"r":{"a":0,"k":0,"ix":10},"sa":{"a":0,"k":0},"o":{"a":1,"k":[{"o":{"x":0.167,"y":0.167},"i":{"x":0.833,"y":0.833},"s":[100],"t":351},{"s":[0],"t":358}],"ix":11}},"ef":[],"t":{"m":{"a":{"a":0,"k":[0,0],"ix":2},"g":1},"p":{},"a":[],"d":{"k":[{"s":{"f":"Montserrat-Bold","s":58,"t":"81%","fc":[0.0549,0.0863,0.0941],"lh":69.6,"tr":0,"j":2,"ca":0},"t":0}]}},"ind":20},{"ty":5,"nm":"Loader Text 82","sr":1,"st":152,"op":154,"ip":152,"hd":false,"ddd":0,"bm":0,"hasMask":false,"ao":0,"ks":{"a":{"a":0,"k":[0,0,0],"ix":1},"s":{"a":0,"k":[100,100,100],"ix":6},"sk":{"a":0,"k":0},"p":{"a":0,"k":[85,50,0],"ix":2},"r":{"a":0,"k":0,"ix":10},"sa":{"a":0,"k":0},"o":{"a":1,"k":[{"o":{"x":0.167,"y":0.167},"i":{"x":0.833,"y":0.833},"s":[100],"t":349},{"s":[0],"t":356}],"ix":11}},"ef":[],"t":{"m":{"a":{"a":0,"k":[0,0],"ix":2},"g":1},"p":{},"a":[],"d":{"k":[{"s":{"f":"Montserrat-Bold","s":58,"t":"80%","fc":[0.0549,0.0863,0.0941],"lh":69.6,"tr":0,"j":2,"ca":0},"t":0}]}},"ind":21},{"ty":5,"nm":"Loader Text 81","sr":1,"st":150,"op":152,"ip":150,"hd":false,"ddd":0,"bm":0,"hasMask":false,"ao":0,"ks":{"a":{"a":0,"k":[0,0,0],"ix":1},"s":{"a":0,"k":[100,100,100],"ix":6},"sk":{"a":0,"k":0},"p":{"a":0,"k":[85,50,0],"ix":2},"r":{"a":0,"k":0,"ix":10},"sa":{"a":0,"k":0},"o":{"a":1,"k":[{"o":{"x":0.167,"y":0.167},"i":{"x":0.833,"y":0.833},"s":[100],"t":347},{"s":[0],"t":354}],"ix":11}},"ef":[],"t":{"m":{"a":{"a":0,"k":[0,0],"ix":2},"g":1},"p":{},"a":[],"d":{"k":[{"s":{"f":"Montserrat-Bold","s":58,"t":"79%","fc":[0.0549,0.0863,0.0941],"lh":69.6,"tr":0,"j":2,"ca":0},"t":0}]}},"ind":22},{"ty":5,"nm":"Loader Text 80","sr":1,"st":149,"op":150,"ip":149,"hd":false,"ddd":0,"bm":0,"hasMask":false,"ao":0,"ks":{"a":{"a":0,"k":[0,0,0],"ix":1},"s":{"a":0,"k":[100,100,100],"ix":6},"sk":{"a":0,"k":0},"p":{"a":0,"k":[85,50,0],"ix":2},"r":{"a":0,"k":0,"ix":10},"sa":{"a":0,"k":0},"o":{"a":1,"k":[{"o":{"x":0.167,"y":0.167},"i":{"x":0.833,"y":0.833},"s":[100],"t":346},{"s":[0],"t":353}],"ix":11}},"ef":[],"t":{"m":{"a":{"a":0,"k":[0,0],"ix":2},"g":1},"p":{},"a":[],"d":{"k":[{"s":{"f":"Montserrat-Bold","s":58,"t":"78%","fc":[0.0549,0.0863,0.0941],"lh":69.6,"tr":0,"j":2,"ca":0},"t":0}]}},"ind":23},{"ty":5,"nm":"Loader Text 79","sr":1,"st":147,"op":149,"ip":147,"hd":false,"ddd":0,"bm":0,"hasMask":false,"ao":0,"ks":{"a":{"a":0,"k":[0,0,0],"ix":1},"s":{"a":0,"k":[100,100,100],"ix":6},"sk":{"a":0,"k":0},"p":{"a":0,"k":[85,50,0],"ix":2},"r":{"a":0,"k":0,"ix":10},"sa":{"a":0,"k":0},"o":{"a":1,"k":[{"o":{"x":0.167,"y":0.167},"i":{"x":0.833,"y":0.833},"s":[100],"t":344},{"s":[0],"t":351}],"ix":11}},"ef":[],"t":{"m":{"a":{"a":0,"k":[0,0],"ix":2},"g":1},"p":{},"a":[],"d":{"k":[{"s":{"f":"Montserrat-Bold","s":58,"t":"77%","fc":[0.0549,0.0863,0.0941],"lh":69.6,"tr":0,"j":2,"ca":0},"t":0}]}},"ind":24},{"ty":5,"nm":"Loader Text 78","sr":1,"st":145,"op":147,"ip":145,"hd":false,"ddd":0,"bm":0,"hasMask":false,"ao":0,"ks":{"a":{"a":0,"k":[0,0,0],"ix":1},"s":{"a":0,"k":[100,100,100],"ix":6},"sk":{"a":0,"k":0},"p":{"a":0,"k":[85,50,0],"ix":2},"r":{"a":0,"k":0,"ix":10},"sa":{"a":0,"k":0},"o":{"a":1,"k":[{"o":{"x":0.167,"y":0.167},"i":{"x":0.833,"y":0.833},"s":[100],"t":342},{"s":[0],"t":349}],"ix":11}},"ef":[],"t":{"m":{"a":{"a":0,"k":[0,0],"ix":2},"g":1},"p":{},"a":[],"d":{"k":[{"s":{"f":"Montserrat-Bold","s":58,"t":"76%","fc":[0.0549,0.0863,0.0941],"lh":69.6,"tr":0,"j":2,"ca":0},"t":0}]}},"ind":25},{"ty":5,"nm":"Loader Text 77","sr":1,"st":143,"op":145,"ip":143,"hd":false,"ddd":0,"bm":0,"hasMask":false,"ao":0,"ks":{"a":{"a":0,"k":[0,0,0],"ix":1},"s":{"a":0,"k":[100,100,100],"ix":6},"sk":{"a":0,"k":0},"p":{"a":0,"k":[85,50,0],"ix":2},"r":{"a":0,"k":0,"ix":10},"sa":{"a":0,"k":0},"o":{"a":1,"k":[{"o":{"x":0.167,"y":0.167},"i":{"x":0.833,"y":0.833},"s":[100],"t":340},{"s":[0],"t":347}],"ix":11}},"ef":[],"t":{"m":{"a":{"a":0,"k":[0,0],"ix":2},"g":1},"p":{},"a":[],"d":{"k":[{"s":{"f":"Montserrat-Bold","s":58,"t":"75%","fc":[0.0549,0.0863,0.0941],"lh":69.6,"tr":0,"j":2,"ca":0},"t":0}]}},"ind":26},{"ty":5,"nm":"Loader Text 76","sr":1,"st":141,"op":143,"ip":141,"hd":false,"ddd":0,"bm":0,"hasMask":false,"ao":0,"ks":{"a":{"a":0,"k":[0,0,0],"ix":1},"s":{"a":0,"k":[100,100,100],"ix":6},"sk":{"a":0,"k":0},"p":{"a":0,"k":[85,50,0],"ix":2},"r":{"a":0,"k":0,"ix":10},"sa":{"a":0,"k":0},"o":{"a":1,"k":[{"o":{"x":0.167,"y":0.167},"i":{"x":0.833,"y":0.833},"s":[100],"t":338},{"s":[0],"t":345}],"ix":11}},"ef":[],"t":{"m":{"a":{"a":0,"k":[0,0],"ix":2},"g":1},"p":{},"a":[],"d":{"k":[{"s":{"f":"Montserrat-Bold","s":58,"t":"74%","fc":[0.0549,0.0863,0.0941],"lh":69.6,"tr":0,"j":2,"ca":0},"t":0}]}},"ind":27},{"ty":5,"nm":"Loader Text 75","sr":1,"st":139,"op":141,"ip":139,"hd":false,"ddd":0,"bm":0,"hasMask":false,"ao":0,"ks":{"a":{"a":0,"k":[0,0,0],"ix":1},"s":{"a":0,"k":[100,100,100],"ix":6},"sk":{"a":0,"k":0},"p":{"a":0,"k":[85,50,0],"ix":2},"r":{"a":0,"k":0,"ix":10},"sa":{"a":0,"k":0},"o":{"a":1,"k":[{"o":{"x":0.167,"y":0.167},"i":{"x":0.833,"y":0.833},"s":[100],"t":336},{"s":[0],"t":343}],"ix":11}},"ef":[],"t":{"m":{"a":{"a":0,"k":[0,0],"ix":2},"g":1},"p":{},"a":[],"d":{"k":[{"s":{"f":"Montserrat-Bold","s":58,"t":"73%","fc":[0.0549,0.0863,0.0941],"lh":69.6,"tr":0,"j":2,"ca":0},"t":0}]}},"ind":28},{"ty":5,"nm":"Loader Text 74","sr":1,"st":137,"op":139,"ip":137,"hd":false,"ddd":0,"bm":0,"hasMask":false,"ao":0,"ks":{"a":{"a":0,"k":[0,0,0],"ix":1},"s":{"a":0,"k":[100,100,100],"ix":6},"sk":{"a":0,"k":0},"p":{"a":0,"k":[85,50,0],"ix":2},"r":{"a":0,"k":0,"ix":10},"sa":{"a":0,"k":0},"o":{"a":1,"k":[{"o":{"x":0.167,"y":0.167},"i":{"x":0.833,"y":0.833},"s":[100],"t":334},{"s":[0],"t":341}],"ix":11}},"ef":[],"t":{"m":{"a":{"a":0,"k":[0,0],"ix":2},"g":1},"p":{},"a":[],"d":{"k":[{"s":{"f":"Montserrat-Bold","s":58,"t":"72%","fc":[0.0549,0.0863,0.0941],"lh":69.6,"tr":0,"j":2,"ca":0},"t":0}]}},"ind":29},{"ty":5,"nm":"Loader Text 73","sr":1,"st":135,"op":137,"ip":135,"hd":false,"ddd":0,"bm":0,"hasMask":false,"ao":0,"ks":{"a":{"a":0,"k":[0,0,0],"ix":1},"s":{"a":0,"k":[100,100,100],"ix":6},"sk":{"a":0,"k":0},"p":{"a":0,"k":[85,50,0],"ix":2},"r":{"a":0,"k":0,"ix":10},"sa":{"a":0,"k":0},"o":{"a":1,"k":[{"o":{"x":0.167,"y":0.167},"i":{"x":0.833,"y":0.833},"s":[100],"t":332},{"s":[0],"t":339}],"ix":11}},"ef":[],"t":{"m":{"a":{"a":0,"k":[0,0],"ix":2},"g":1},"p":{},"a":[],"d":{"k":[{"s":{"f":"Montserrat-Bold","s":58,"t":"71%","fc":[0.0549,0.0863,0.0941],"lh":69.6,"tr":0,"j":2,"ca":0},"t":0}]}},"ind":30},{"ty":5,"nm":"Loader Text 72","sr":1,"st":133,"op":135,"ip":133,"hd":false,"ddd":0,"bm":0,"hasMask":false,"ao":0,"ks":{"a":{"a":0,"k":[0,0,0],"ix":1},"s":{"a":0,"k":[100,100,100],"ix":6},"sk":{"a":0,"k":0},"p":{"a":0,"k":[85,50,0],"ix":2},"r":{"a":0,"k":0,"ix":10},"sa":{"a":0,"k":0},"o":{"a":1,"k":[{"o":{"x":0.167,"y":0.167},"i":{"x":0.833,"y":0.833},"s":[100],"t":330},{"s":[0],"t":337}],"ix":11}},"ef":[],"t":{"m":{"a":{"a":0,"k":[0,0],"ix":2},"g":1},"p":{},"a":[],"d":{"k":[{"s":{"f":"Montserrat-Bold","s":58,"t":"70%","fc":[0.0549,0.0863,0.0941],"lh":69.6,"tr":0,"j":2,"ca":0},"t":0}]}},"ind":31},{"ty":5,"nm":"Loader Text 71","sr":1,"st":131,"op":133,"ip":131,"hd":false,"ddd":0,"bm":0,"hasMask":false,"ao":0,"ks":{"a":{"a":0,"k":[0,0,0],"ix":1},"s":{"a":0,"k":[100,100,100],"ix":6},"sk":{"a":0,"k":0},"p":{"a":0,"k":[85,50,0],"ix":2},"r":{"a":0,"k":0,"ix":10},"sa":{"a":0,"k":0},"o":{"a":1,"k":[{"o":{"x":0.167,"y":0.167},"i":{"x":0.833,"y":0.833},"s":[100],"t":328},{"s":[0],"t":335}],"ix":11}},"ef":[],"t":{"m":{"a":{"a":0,"k":[0,0],"ix":2},"g":1},"p":{},"a":[],"d":{"k":[{"s":{"f":"Montserrat-Bold","s":58,"t":"69%","fc":[0.0549,0.0863,0.0941],"lh":69.6,"tr":0,"j":2,"ca":0},"t":0}]}},"ind":32},{"ty":5,"nm":"Loader Text 70","sr":1,"st":129,"op":131,"ip":129,"hd":false,"ddd":0,"bm":0,"hasMask":false,"ao":0,"ks":{"a":{"a":0,"k":[0,0,0],"ix":1},"s":{"a":0,"k":[100,100,100],"ix":6},"sk":{"a":0,"k":0},"p":{"a":0,"k":[85,50,0],"ix":2},"r":{"a":0,"k":0,"ix":10},"sa":{"a":0,"k":0},"o":{"a":1,"k":[{"o":{"x":0.167,"y":0.167},"i":{"x":0.833,"y":0.833},"s":[100],"t":326},{"s":[0],"t":333}],"ix":11}},"ef":[],"t":{"m":{"a":{"a":0,"k":[0,0],"ix":2},"g":1},"p":{},"a":[],"d":{"k":[{"s":{"f":"Montserrat-Bold","s":58,"t":"68%","fc":[0.0549,0.0863,0.0941],"lh":69.6,"tr":0,"j":2,"ca":0},"t":0}]}},"ind":33},{"ty":5,"nm":"Loader Text 69","sr":1,"st":128,"op":129,"ip":128,"hd":false,"ddd":0,"bm":0,"hasMask":false,"ao":0,"ks":{"a":{"a":0,"k":[0,0,0],"ix":1},"s":{"a":0,"k":[100,100,100],"ix":6},"sk":{"a":0,"k":0},"p":{"a":0,"k":[85,50,0],"ix":2},"r":{"a":0,"k":0,"ix":10},"sa":{"a":0,"k":0},"o":{"a":1,"k":[{"o":{"x":0.167,"y":0.167},"i":{"x":0.833,"y":0.833},"s":[100],"t":325},{"s":[0],"t":332}],"ix":11}},"ef":[],"t":{"m":{"a":{"a":0,"k":[0,0],"ix":2},"g":1},"p":{},"a":[],"d":{"k":[{"s":{"f":"Montserrat-Bold","s":58,"t":"67%","fc":[0.0549,0.0863,0.0941],"lh":69.6,"tr":0,"j":2,"ca":0},"t":0}]}},"ind":34},{"ty":5,"nm":"Loader Text 68","sr":1,"st":126,"op":128,"ip":126,"hd":false,"ddd":0,"bm":0,"hasMask":false,"ao":0,"ks":{"a":{"a":0,"k":[0,0,0],"ix":1},"s":{"a":0,"k":[100,100,100],"ix":6},"sk":{"a":0,"k":0},"p":{"a":0,"k":[85,50,0],"ix":2},"r":{"a":0,"k":0,"ix":10},"sa":{"a":0,"k":0},"o":{"a":1,"k":[{"o":{"x":0.167,"y":0.167},"i":{"x":0.833,"y":0.833},"s":[100],"t":323},{"s":[0],"t":330}],"ix":11}},"ef":[],"t":{"m":{"a":{"a":0,"k":[0,0],"ix":2},"g":1},"p":{},"a":[],"d":{"k":[{"s":{"f":"Montserrat-Bold","s":58,"t":"66%","fc":[0.0549,0.0863,0.0941],"lh":69.6,"tr":0,"j":2,"ca":0},"t":0}]}},"ind":35},{"ty":5,"nm":"Loader Text 67","sr":1,"st":124,"op":126,"ip":124,"hd":false,"ddd":0,"bm":0,"hasMask":false,"ao":0,"ks":{"a":{"a":0,"k":[0,0,0],"ix":1},"s":{"a":0,"k":[100,100,100],"ix":6},"sk":{"a":0,"k":0},"p":{"a":0,"k":[85,50,0],"ix":2},"r":{"a":0,"k":0,"ix":10},"sa":{"a":0,"k":0},"o":{"a":1,"k":[{"o":{"x":0.167,"y":0.167},"i":{"x":0.833,"y":0.833},"s":[100],"t":321},{"s":[0],"t":328}],"ix":11}},"ef":[],"t":{"m":{"a":{"a":0,"k":[0,0],"ix":2},"g":1},"p":{},"a":[],"d":{"k":[{"s":{"f":"Montserrat-Bold","s":58,"t":"65%","fc":[0.0549,0.0863,0.0941],"lh":69.6,"tr":0,"j":2,"ca":0},"t":0}]}},"ind":36},{"ty":5,"nm":"Loader Text 66","sr":1,"st":122,"op":124,"ip":122,"hd":false,"ddd":0,"bm":0,"hasMask":false,"ao":0,"ks":{"a":{"a":0,"k":[0,0,0],"ix":1},"s":{"a":0,"k":[100,100,100],"ix":6},"sk":{"a":0,"k":0},"p":{"a":0,"k":[85,50,0],"ix":2},"r":{"a":0,"k":0,"ix":10},"sa":{"a":0,"k":0},"o":{"a":1,"k":[{"o":{"x":0.167,"y":0.167},"i":{"x":0.833,"y":0.833},"s":[100],"t":319},{"s":[0],"t":326}],"ix":11}},"ef":[],"t":{"m":{"a":{"a":0,"k":[0,0],"ix":2},"g":1},"p":{},"a":[],"d":{"k":[{"s":{"f":"Montserrat-Bold","s":58,"t":"64%","fc":[0.0549,0.0863,0.0941],"lh":69.6,"tr":0,"j":2,"ca":0},"t":0}]}},"ind":37},{"ty":5,"nm":"Loader Text 65","sr":1,"st":120,"op":122,"ip":120,"hd":false,"ddd":0,"bm":0,"hasMask":false,"ao":0,"ks":{"a":{"a":0,"k":[0,0,0],"ix":1},"s":{"a":0,"k":[100,100,100],"ix":6},"sk":{"a":0,"k":0},"p":{"a":0,"k":[85,50,0],"ix":2},"r":{"a":0,"k":0,"ix":10},"sa":{"a":0,"k":0},"o":{"a":1,"k":[{"o":{"x":0.167,"y":0.167},"i":{"x":0.833,"y":0.833},"s":[100],"t":317},{"s":[0],"t":324}],"ix":11}},"ef":[],"t":{"m":{"a":{"a":0,"k":[0,0],"ix":2},"g":1},"p":{},"a":[],"d":{"k":[{"s":{"f":"Montserrat-Bold","s":58,"t":"63%","fc":[0.0549,0.0863,0.0941],"lh":69.6,"tr":0,"j":2,"ca":0},"t":0}]}},"ind":38},{"ty":5,"nm":"Loader Text 64","sr":1,"st":118,"op":120,"ip":118,"hd":false,"ddd":0,"bm":0,"hasMask":false,"ao":0,"ks":{"a":{"a":0,"k":[0,0,0],"ix":1},"s":{"a":0,"k":[100,100,100],"ix":6},"sk":{"a":0,"k":0},"p":{"a":0,"k":[85,50,0],"ix":2},"r":{"a":0,"k":0,"ix":10},"sa":{"a":0,"k":0},"o":{"a":1,"k":[{"o":{"x":0.167,"y":0.167},"i":{"x":0.833,"y":0.833},"s":[100],"t":315},{"s":[0],"t":322}],"ix":11}},"ef":[],"t":{"m":{"a":{"a":0,"k":[0,0],"ix":2},"g":1},"p":{},"a":[],"d":{"k":[{"s":{"f":"Montserrat-Bold","s":58,"t":"62%","fc":[0.0549,0.0863,0.0941],"lh":69.6,"tr":0,"j":2,"ca":0},"t":0}]}},"ind":39},{"ty":5,"nm":"Loader Text 63","sr":1,"st":116,"op":118,"ip":116,"hd":false,"ddd":0,"bm":0,"hasMask":false,"ao":0,"ks":{"a":{"a":0,"k":[0,0,0],"ix":1},"s":{"a":0,"k":[100,100,100],"ix":6},"sk":{"a":0,"k":0},"p":{"a":0,"k":[85,50,0],"ix":2},"r":{"a":0,"k":0,"ix":10},"sa":{"a":0,"k":0},"o":{"a":1,"k":[{"o":{"x":0.167,"y":0.167},"i":{"x":0.833,"y":0.833},"s":[100],"t":313},{"s":[0],"t":320}],"ix":11}},"ef":[],"t":{"m":{"a":{"a":0,"k":[0,0],"ix":2},"g":1},"p":{},"a":[],"d":{"k":[{"s":{"f":"Montserrat-Bold","s":58,"t":"61%","fc":[0.0549,0.0863,0.0941],"lh":69.6,"tr":0,"j":2,"ca":0},"t":0}]}},"ind":40},{"ty":5,"nm":"Loader Text 62","sr":1,"st":114,"op":116,"ip":114,"hd":false,"ddd":0,"bm":0,"hasMask":false,"ao":0,"ks":{"a":{"a":0,"k":[0,0,0],"ix":1},"s":{"a":0,"k":[100,100,100],"ix":6},"sk":{"a":0,"k":0},"p":{"a":0,"k":[85,50,0],"ix":2},"r":{"a":0,"k":0,"ix":10},"sa":{"a":0,"k":0},"o":{"a":1,"k":[{"o":{"x":0.167,"y":0.167},"i":{"x":0.833,"y":0.833},"s":[100],"t":311},{"s":[0],"t":318}],"ix":11}},"ef":[],"t":{"m":{"a":{"a":0,"k":[0,0],"ix":2},"g":1},"p":{},"a":[],"d":{"k":[{"s":{"f":"Montserrat-Bold","s":58,"t":"60%","fc":[0.0549,0.0863,0.0941],"lh":69.6,"tr":0,"j":2,"ca":0},"t":0}]}},"ind":41},{"ty":5,"nm":"Loader Text 61","sr":1,"st":112,"op":114,"ip":112,"hd":false,"ddd":0,"bm":0,"hasMask":false,"ao":0,"ks":{"a":{"a":0,"k":[0,0,0],"ix":1},"s":{"a":0,"k":[100,100,100],"ix":6},"sk":{"a":0,"k":0},"p":{"a":0,"k":[85,50,0],"ix":2},"r":{"a":0,"k":0,"ix":10},"sa":{"a":0,"k":0},"o":{"a":1,"k":[{"o":{"x":0.167,"y":0.167},"i":{"x":0.833,"y":0.833},"s":[100],"t":309},{"s":[0],"t":316}],"ix":11}},"ef":[],"t":{"m":{"a":{"a":0,"k":[0,0],"ix":2},"g":1},"p":{},"a":[],"d":{"k":[{"s":{"f":"Montserrat-Bold","s":58,"t":"59%","fc":[0.0549,0.0863,0.0941],"lh":69.6,"tr":0,"j":2,"ca":0},"t":0}]}},"ind":42},{"ty":5,"nm":"Loader Text 60","sr":1,"st":110,"op":112,"ip":110,"hd":false,"ddd":0,"bm":0,"hasMask":false,"ao":0,"ks":{"a":{"a":0,"k":[0,0,0],"ix":1},"s":{"a":0,"k":[100,100,100],"ix":6},"sk":{"a":0,"k":0},"p":{"a":0,"k":[85,50,0],"ix":2},"r":{"a":0,"k":0,"ix":10},"sa":{"a":0,"k":0},"o":{"a":1,"k":[{"o":{"x":0.167,"y":0.167},"i":{"x":0.833,"y":0.833},"s":[100],"t":307},{"s":[0],"t":314}],"ix":11}},"ef":[],"t":{"m":{"a":{"a":0,"k":[0,0],"ix":2},"g":1},"p":{},"a":[],"d":{"k":[{"s":{"f":"Montserrat-Bold","s":58,"t":"58%","fc":[0.0549,0.0863,0.0941],"lh":69.6,"tr":0,"j":2,"ca":0},"t":0}]}},"ind":43},{"ty":5,"nm":"Loader Text 59","sr":1,"st":108,"op":110,"ip":108,"hd":false,"ddd":0,"bm":0,"hasMask":false,"ao":0,"ks":{"a":{"a":0,"k":[0,0,0],"ix":1},"s":{"a":0,"k":[100,100,100],"ix":6},"sk":{"a":0,"k":0},"p":{"a":0,"k":[85,50,0],"ix":2},"r":{"a":0,"k":0,"ix":10},"sa":{"a":0,"k":0},"o":{"a":1,"k":[{"o":{"x":0.167,"y":0.167},"i":{"x":0.833,"y":0.833},"s":[100],"t":305},{"s":[0],"t":312}],"ix":11}},"ef":[],"t":{"m":{"a":{"a":0,"k":[0,0],"ix":2},"g":1},"p":{},"a":[],"d":{"k":[{"s":{"f":"Montserrat-Bold","s":58,"t":"57%","fc":[0.0549,0.0863,0.0941],"lh":69.6,"tr":0,"j":2,"ca":0},"t":0}]}},"ind":44},{"ty":5,"nm":"Loader Text 58","sr":1,"st":107,"op":108,"ip":107,"hd":false,"ddd":0,"bm":0,"hasMask":false,"ao":0,"ks":{"a":{"a":0,"k":[0,0,0],"ix":1},"s":{"a":0,"k":[100,100,100],"ix":6},"sk":{"a":0,"k":0},"p":{"a":0,"k":[85,50,0],"ix":2},"r":{"a":0,"k":0,"ix":10},"sa":{"a":0,"k":0},"o":{"a":1,"k":[{"o":{"x":0.167,"y":0.167},"i":{"x":0.833,"y":0.833},"s":[100],"t":304},{"s":[0],"t":311}],"ix":11}},"ef":[],"t":{"m":{"a":{"a":0,"k":[0,0],"ix":2},"g":1},"p":{},"a":[],"d":{"k":[{"s":{"f":"Montserrat-Bold","s":58,"t":"56%","fc":[0.0549,0.0863,0.0941],"lh":69.6,"tr":0,"j":2,"ca":0},"t":0}]}},"ind":45},{"ty":5,"nm":"Loader Text 57","sr":1,"st":105,"op":107,"ip":105,"hd":false,"ddd":0,"bm":0,"hasMask":false,"ao":0,"ks":{"a":{"a":0,"k":[0,0,0],"ix":1},"s":{"a":0,"k":[100,100,100],"ix":6},"sk":{"a":0,"k":0},"p":{"a":0,"k":[85,50,0],"ix":2},"r":{"a":0,"k":0,"ix":10},"sa":{"a":0,"k":0},"o":{"a":1,"k":[{"o":{"x":0.167,"y":0.167},"i":{"x":0.833,"y":0.833},"s":[100],"t":302},{"s":[0],"t":309}],"ix":11}},"ef":[],"t":{"m":{"a":{"a":0,"k":[0,0],"ix":2},"g":1},"p":{},"a":[],"d":{"k":[{"s":{"f":"Montserrat-Bold","s":58,"t":"55%","fc":[0.0549,0.0863,0.0941],"lh":69.6,"tr":0,"j":2,"ca":0},"t":0}]}},"ind":46},{"ty":5,"nm":"Loader Text 56","sr":1,"st":103,"op":105,"ip":103,"hd":false,"ddd":0,"bm":0,"hasMask":false,"ao":0,"ks":{"a":{"a":0,"k":[0,0,0],"ix":1},"s":{"a":0,"k":[100,100,100],"ix":6},"sk":{"a":0,"k":0},"p":{"a":0,"k":[85,50,0],"ix":2},"r":{"a":0,"k":0,"ix":10},"sa":{"a":0,"k":0},"o":{"a":1,"k":[{"o":{"x":0.167,"y":0.167},"i":{"x":0.833,"y":0.833},"s":[100],"t":300},{"s":[0],"t":307}],"ix":11}},"ef":[],"t":{"m":{"a":{"a":0,"k":[0,0],"ix":2},"g":1},"p":{},"a":[],"d":{"k":[{"s":{"f":"Montserrat-Bold","s":58,"t":"54%","fc":[0.0549,0.0863,0.0941],"lh":69.6,"tr":0,"j":2,"ca":0},"t":0}]}},"ind":47},{"ty":5,"nm":"Loader Text 55","sr":1,"st":101,"op":103,"ip":101,"hd":false,"ddd":0,"bm":0,"hasMask":false,"ao":0,"ks":{"a":{"a":0,"k":[0,0,0],"ix":1},"s":{"a":0,"k":[100,100,100],"ix":6},"sk":{"a":0,"k":0},"p":{"a":0,"k":[85,50,0],"ix":2},"r":{"a":0,"k":0,"ix":10},"sa":{"a":0,"k":0},"o":{"a":1,"k":[{"o":{"x":0.167,"y":0.167},"i":{"x":0.833,"y":0.833},"s":[100],"t":298},{"s":[0],"t":305}],"ix":11}},"ef":[],"t":{"m":{"a":{"a":0,"k":[0,0],"ix":2},"g":1},"p":{},"a":[],"d":{"k":[{"s":{"f":"Montserrat-Bold","s":58,"t":"53%","fc":[0.0549,0.0863,0.0941],"lh":69.6,"tr":0,"j":2,"ca":0},"t":0}]}},"ind":48},{"ty":5,"nm":"Loader Text 54","sr":1,"st":99,"op":101,"ip":99,"hd":false,"ddd":0,"bm":0,"hasMask":false,"ao":0,"ks":{"a":{"a":0,"k":[0,0,0],"ix":1},"s":{"a":0,"k":[100,100,100],"ix":6},"sk":{"a":0,"k":0},"p":{"a":0,"k":[85,50,0],"ix":2},"r":{"a":0,"k":0,"ix":10},"sa":{"a":0,"k":0},"o":{"a":1,"k":[{"o":{"x":0.167,"y":0.167},"i":{"x":0.833,"y":0.833},"s":[100],"t":296},{"s":[0],"t":303}],"ix":11}},"ef":[],"t":{"m":{"a":{"a":0,"k":[0,0],"ix":2},"g":1},"p":{},"a":[],"d":{"k":[{"s":{"f":"Montserrat-Bold","s":58,"t":"52%","fc":[0.0549,0.0863,0.0941],"lh":69.6,"tr":0,"j":2,"ca":0},"t":0}]}},"ind":49},{"ty":5,"nm":"Loader Text 53","sr":1,"st":97,"op":99,"ip":97,"hd":false,"ddd":0,"bm":0,"hasMask":false,"ao":0,"ks":{"a":{"a":0,"k":[0,0,0],"ix":1},"s":{"a":0,"k":[100,100,100],"ix":6},"sk":{"a":0,"k":0},"p":{"a":0,"k":[85,50,0],"ix":2},"r":{"a":0,"k":0,"ix":10},"sa":{"a":0,"k":0},"o":{"a":1,"k":[{"o":{"x":0.167,"y":0.167},"i":{"x":0.833,"y":0.833},"s":[100],"t":294},{"s":[0],"t":301}],"ix":11}},"ef":[],"t":{"m":{"a":{"a":0,"k":[0,0],"ix":2},"g":1},"p":{},"a":[],"d":{"k":[{"s":{"f":"Montserrat-Bold","s":58,"t":"51%","fc":[0.0549,0.0863,0.0941],"lh":69.6,"tr":0,"j":2,"ca":0},"t":0}]}},"ind":50},{"ty":5,"nm":"Loader Text 52","sr":1,"st":95,"op":97,"ip":95,"hd":false,"ddd":0,"bm":0,"hasMask":false,"ao":0,"ks":{"a":{"a":0,"k":[0,0,0],"ix":1},"s":{"a":0,"k":[100,100,100],"ix":6},"sk":{"a":0,"k":0},"p":{"a":0,"k":[85,50,0],"ix":2},"r":{"a":0,"k":0,"ix":10},"sa":{"a":0,"k":0},"o":{"a":1,"k":[{"o":{"x":0.167,"y":0.167},"i":{"x":0.833,"y":0.833},"s":[100],"t":292},{"s":[0],"t":299}],"ix":11}},"ef":[],"t":{"m":{"a":{"a":0,"k":[0,0],"ix":2},"g":1},"p":{},"a":[],"d":{"k":[{"s":{"f":"Montserrat-Bold","s":58,"t":"50%","fc":[0.0549,0.0863,0.0941],"lh":69.6,"tr":0,"j":2,"ca":0},"t":0}]}},"ind":51},{"ty":5,"nm":"Loader Text 51","sr":1,"st":93,"op":95,"ip":93,"hd":false,"ddd":0,"bm":0,"hasMask":false,"ao":0,"ks":{"a":{"a":0,"k":[0,0,0],"ix":1},"s":{"a":0,"k":[100,100,100],"ix":6},"sk":{"a":0,"k":0},"p":{"a":0,"k":[85,50,0],"ix":2},"r":{"a":0,"k":0,"ix":10},"sa":{"a":0,"k":0},"o":{"a":1,"k":[{"o":{"x":0.167,"y":0.167},"i":{"x":0.833,"y":0.833},"s":[100],"t":290},{"s":[0],"t":297}],"ix":11}},"ef":[],"t":{"m":{"a":{"a":0,"k":[0,0],"ix":2},"g":1},"p":{},"a":[],"d":{"k":[{"s":{"f":"Montserrat-Bold","s":58,"t":"49%","fc":[0.0549,0.0863,0.0941],"lh":69.6,"tr":0,"j":2,"ca":0},"t":0}]}},"ind":52},{"ty":5,"nm":"Loader Text 50","sr":1,"st":91,"op":93,"ip":91,"hd":false,"ddd":0,"bm":0,"hasMask":false,"ao":0,"ks":{"a":{"a":0,"k":[0,0,0],"ix":1},"s":{"a":0,"k":[100,100,100],"ix":6},"sk":{"a":0,"k":0},"p":{"a":0,"k":[85,50,0],"ix":2},"r":{"a":0,"k":0,"ix":10},"sa":{"a":0,"k":0},"o":{"a":1,"k":[{"o":{"x":0.167,"y":0.167},"i":{"x":0.833,"y":0.833},"s":[100],"t":288},{"s":[0],"t":295}],"ix":11}},"ef":[],"t":{"m":{"a":{"a":0,"k":[0,0],"ix":2},"g":1},"p":{},"a":[],"d":{"k":[{"s":{"f":"Montserrat-Bold","s":58,"t":"48%","fc":[0.0549,0.0863,0.0941],"lh":69.6,"tr":0,"j":2,"ca":0},"t":0}]}},"ind":53},{"ty":5,"nm":"Loader Text 49","sr":1,"st":89,"op":91,"ip":89,"hd":false,"ddd":0,"bm":0,"hasMask":false,"ao":0,"ks":{"a":{"a":0,"k":[0,0,0],"ix":1},"s":{"a":0,"k":[100,100,100],"ix":6},"sk":{"a":0,"k":0},"p":{"a":0,"k":[85,50,0],"ix":2},"r":{"a":0,"k":0,"ix":10},"sa":{"a":0,"k":0},"o":{"a":1,"k":[{"o":{"x":0.167,"y":0.167},"i":{"x":0.833,"y":0.833},"s":[100],"t":286},{"s":[0],"t":293}],"ix":11}},"ef":[],"t":{"m":{"a":{"a":0,"k":[0,0],"ix":2},"g":1},"p":{},"a":[],"d":{"k":[{"s":{"f":"Montserrat-Bold","s":58,"t":"47%","fc":[0.0549,0.0863,0.0941],"lh":69.6,"tr":0,"j":2,"ca":0},"t":0}]}},"ind":54},{"ty":5,"nm":"Loader Text 48","sr":1,"st":87,"op":89,"ip":87,"hd":false,"ddd":0,"bm":0,"hasMask":false,"ao":0,"ks":{"a":{"a":0,"k":[0,0,0],"ix":1},"s":{"a":0,"k":[100,100,100],"ix":6},"sk":{"a":0,"k":0},"p":{"a":0,"k":[85,50,0],"ix":2},"r":{"a":0,"k":0,"ix":10},"sa":{"a":0,"k":0},"o":{"a":1,"k":[{"o":{"x":0.167,"y":0.167},"i":{"x":0.833,"y":0.833},"s":[100],"t":284},{"s":[0],"t":291}],"ix":11}},"ef":[],"t":{"m":{"a":{"a":0,"k":[0,0],"ix":2},"g":1},"p":{},"a":[],"d":{"k":[{"s":{"f":"Montserrat-Bold","s":58,"t":"46%","fc":[0.0549,0.0863,0.0941],"lh":69.6,"tr":0,"j":2,"ca":0},"t":0}]}},"ind":55},{"ty":5,"nm":"Loader Text 47","sr":1,"st":85,"op":87,"ip":85,"hd":false,"ddd":0,"bm":0,"hasMask":false,"ao":0,"ks":{"a":{"a":0,"k":[0,0,0],"ix":1},"s":{"a":0,"k":[100,100,100],"ix":6},"sk":{"a":0,"k":0},"p":{"a":0,"k":[85,50,0],"ix":2},"r":{"a":0,"k":0,"ix":10},"sa":{"a":0,"k":0},"o":{"a":1,"k":[{"o":{"x":0.167,"y":0.167},"i":{"x":0.833,"y":0.833},"s":[100],"t":282},{"s":[0],"t":289}],"ix":11}},"ef":[],"t":{"m":{"a":{"a":0,"k":[0,0],"ix":2},"g":1},"p":{},"a":[],"d":{"k":[{"s":{"f":"Montserrat-Bold","s":58,"t":"45%","fc":[0.0549,0.0863,0.0941],"lh":69.6,"tr":0,"j":2,"ca":0},"t":0}]}},"ind":56},{"ty":5,"nm":"Loader Text 46","sr":1,"st":84,"op":85,"ip":84,"hd":false,"ddd":0,"bm":0,"hasMask":false,"ao":0,"ks":{"a":{"a":0,"k":[0,0,0],"ix":1},"s":{"a":0,"k":[100,100,100],"ix":6},"sk":{"a":0,"k":0},"p":{"a":0,"k":[85,50,0],"ix":2},"r":{"a":0,"k":0,"ix":10},"sa":{"a":0,"k":0},"o":{"a":1,"k":[{"o":{"x":0.167,"y":0.167},"i":{"x":0.833,"y":0.833},"s":[100],"t":281},{"s":[0],"t":288}],"ix":11}},"ef":[],"t":{"m":{"a":{"a":0,"k":[0,0],"ix":2},"g":1},"p":{},"a":[],"d":{"k":[{"s":{"f":"Montserrat-Bold","s":58,"t":"44%","fc":[0.0549,0.0863,0.0941],"lh":69.6,"tr":0,"j":2,"ca":0},"t":0}]}},"ind":57},{"ty":5,"nm":"Loader Text 45","sr":1,"st":82,"op":84,"ip":82,"hd":false,"ddd":0,"bm":0,"hasMask":false,"ao":0,"ks":{"a":{"a":0,"k":[0,0,0],"ix":1},"s":{"a":0,"k":[100,100,100],"ix":6},"sk":{"a":0,"k":0},"p":{"a":0,"k":[85,50,0],"ix":2},"r":{"a":0,"k":0,"ix":10},"sa":{"a":0,"k":0},"o":{"a":1,"k":[{"o":{"x":0.167,"y":0.167},"i":{"x":0.833,"y":0.833},"s":[100],"t":279},{"s":[0],"t":286}],"ix":11}},"ef":[],"t":{"m":{"a":{"a":0,"k":[0,0],"ix":2},"g":1},"p":{},"a":[],"d":{"k":[{"s":{"f":"Montserrat-Bold","s":58,"t":"43%","fc":[0.0549,0.0863,0.0941],"lh":69.6,"tr":0,"j":2,"ca":0},"t":0}]}},"ind":58},{"ty":5,"nm":"Loader Text 44","sr":1,"st":80,"op":82,"ip":80,"hd":false,"ddd":0,"bm":0,"hasMask":false,"ao":0,"ks":{"a":{"a":0,"k":[0,0,0],"ix":1},"s":{"a":0,"k":[100,100,100],"ix":6},"sk":{"a":0,"k":0},"p":{"a":0,"k":[85,50,0],"ix":2},"r":{"a":0,"k":0,"ix":10},"sa":{"a":0,"k":0},"o":{"a":1,"k":[{"o":{"x":0.167,"y":0.167},"i":{"x":0.833,"y":0.833},"s":[100],"t":277},{"s":[0],"t":284}],"ix":11}},"ef":[],"t":{"m":{"a":{"a":0,"k":[0,0],"ix":2},"g":1},"p":{},"a":[],"d":{"k":[{"s":{"f":"Montserrat-Bold","s":58,"t":"42%","fc":[0.0549,0.0863,0.0941],"lh":69.6,"tr":0,"j":2,"ca":0},"t":0}]}},"ind":59},{"ty":5,"nm":"Loader Text 43","sr":1,"st":78,"op":80,"ip":78,"hd":false,"ddd":0,"bm":0,"hasMask":false,"ao":0,"ks":{"a":{"a":0,"k":[0,0,0],"ix":1},"s":{"a":0,"k":[100,100,100],"ix":6},"sk":{"a":0,"k":0},"p":{"a":0,"k":[85,50,0],"ix":2},"r":{"a":0,"k":0,"ix":10},"sa":{"a":0,"k":0},"o":{"a":1,"k":[{"o":{"x":0.167,"y":0.167},"i":{"x":0.833,"y":0.833},"s":[100],"t":275},{"s":[0],"t":282}],"ix":11}},"ef":[],"t":{"m":{"a":{"a":0,"k":[0,0],"ix":2},"g":1},"p":{},"a":[],"d":{"k":[{"s":{"f":"Montserrat-Bold","s":58,"t":"41%","fc":[0.0549,0.0863,0.0941],"lh":69.6,"tr":0,"j":2,"ca":0},"t":0}]}},"ind":60},{"ty":5,"nm":"Loader Text 42","sr":1,"st":76,"op":78,"ip":76,"hd":false,"ddd":0,"bm":0,"hasMask":false,"ao":0,"ks":{"a":{"a":0,"k":[0,0,0],"ix":1},"s":{"a":0,"k":[100,100,100],"ix":6},"sk":{"a":0,"k":0},"p":{"a":0,"k":[85,50,0],"ix":2},"r":{"a":0,"k":0,"ix":10},"sa":{"a":0,"k":0},"o":{"a":1,"k":[{"o":{"x":0.167,"y":0.167},"i":{"x":0.833,"y":0.833},"s":[100],"t":273},{"s":[0],"t":280}],"ix":11}},"ef":[],"t":{"m":{"a":{"a":0,"k":[0,0],"ix":2},"g":1},"p":{},"a":[],"d":{"k":[{"s":{"f":"Montserrat-Bold","s":58,"t":"40%","fc":[0.0549,0.0863,0.0941],"lh":69.6,"tr":0,"j":2,"ca":0},"t":0}]}},"ind":61},{"ty":5,"nm":"Loader Text 41","sr":1,"st":74,"op":76,"ip":74,"hd":false,"ddd":0,"bm":0,"hasMask":false,"ao":0,"ks":{"a":{"a":0,"k":[0,0,0],"ix":1},"s":{"a":0,"k":[100,100,100],"ix":6},"sk":{"a":0,"k":0},"p":{"a":0,"k":[85,50,0],"ix":2},"r":{"a":0,"k":0,"ix":10},"sa":{"a":0,"k":0},"o":{"a":1,"k":[{"o":{"x":0.167,"y":0.167},"i":{"x":0.833,"y":0.833},"s":[100],"t":271},{"s":[0],"t":278}],"ix":11}},"ef":[],"t":{"m":{"a":{"a":0,"k":[0,0],"ix":2},"g":1},"p":{},"a":[],"d":{"k":[{"s":{"f":"Montserrat-Bold","s":58,"t":"39%","fc":[0.0549,0.0863,0.0941],"lh":69.6,"tr":0,"j":2,"ca":0},"t":0}]}},"ind":62},{"ty":5,"nm":"Loader Text 40","sr":1,"st":72,"op":74,"ip":72,"hd":false,"ddd":0,"bm":0,"hasMask":false,"ao":0,"ks":{"a":{"a":0,"k":[0,0,0],"ix":1},"s":{"a":0,"k":[100,100,100],"ix":6},"sk":{"a":0,"k":0},"p":{"a":0,"k":[85,50,0],"ix":2},"r":{"a":0,"k":0,"ix":10},"sa":{"a":0,"k":0},"o":{"a":1,"k":[{"o":{"x":0.167,"y":0.167},"i":{"x":0.833,"y":0.833},"s":[100],"t":269},{"s":[0],"t":276}],"ix":11}},"ef":[],"t":{"m":{"a":{"a":0,"k":[0,0],"ix":2},"g":1},"p":{},"a":[],"d":{"k":[{"s":{"f":"Montserrat-Bold","s":58,"t":"38%","fc":[0.0549,0.0863,0.0941],"lh":69.6,"tr":0,"j":2,"ca":0},"t":0}]}},"ind":63},{"ty":5,"nm":"Loader Text 39","sr":1,"st":70,"op":72,"ip":70,"hd":false,"ddd":0,"bm":0,"hasMask":false,"ao":0,"ks":{"a":{"a":0,"k":[0,0,0],"ix":1},"s":{"a":0,"k":[100,100,100],"ix":6},"sk":{"a":0,"k":0},"p":{"a":0,"k":[85,50,0],"ix":2},"r":{"a":0,"k":0,"ix":10},"sa":{"a":0,"k":0},"o":{"a":1,"k":[{"o":{"x":0.167,"y":0.167},"i":{"x":0.833,"y":0.833},"s":[100],"t":267},{"s":[0],"t":274}],"ix":11}},"ef":[],"t":{"m":{"a":{"a":0,"k":[0,0],"ix":2},"g":1},"p":{},"a":[],"d":{"k":[{"s":{"f":"Montserrat-Bold","s":58,"t":"37%","fc":[0.0549,0.0863,0.0941],"lh":69.6,"tr":0,"j":2,"ca":0},"t":0}]}},"ind":64},{"ty":5,"nm":"Loader Text 38","sr":1,"st":68,"op":70,"ip":68,"hd":false,"ddd":0,"bm":0,"hasMask":false,"ao":0,"ks":{"a":{"a":0,"k":[0,0,0],"ix":1},"s":{"a":0,"k":[100,100,100],"ix":6},"sk":{"a":0,"k":0},"p":{"a":0,"k":[85,50,0],"ix":2},"r":{"a":0,"k":0,"ix":10},"sa":{"a":0,"k":0},"o":{"a":1,"k":[{"o":{"x":0.167,"y":0.167},"i":{"x":0.833,"y":0.833},"s":[100],"t":265},{"s":[0],"t":272}],"ix":11}},"ef":[],"t":{"m":{"a":{"a":0,"k":[0,0],"ix":2},"g":1},"p":{},"a":[],"d":{"k":[{"s":{"f":"Montserrat-Bold","s":58,"t":"36%","fc":[0.0549,0.0863,0.0941],"lh":69.6,"tr":0,"j":2,"ca":0},"t":0}]}},"ind":65},{"ty":5,"nm":"Loader Text 37","sr":1,"st":66,"op":68,"ip":66,"hd":false,"ddd":0,"bm":0,"hasMask":false,"ao":0,"ks":{"a":{"a":0,"k":[0,0,0],"ix":1},"s":{"a":0,"k":[100,100,100],"ix":6},"sk":{"a":0,"k":0},"p":{"a":0,"k":[85,50,0],"ix":2},"r":{"a":0,"k":0,"ix":10},"sa":{"a":0,"k":0},"o":{"a":1,"k":[{"o":{"x":0.167,"y":0.167},"i":{"x":0.833,"y":0.833},"s":[100],"t":263},{"s":[0],"t":270}],"ix":11}},"ef":[],"t":{"m":{"a":{"a":0,"k":[0,0],"ix":2},"g":1},"p":{},"a":[],"d":{"k":[{"s":{"f":"Montserrat-Bold","s":58,"t":"35%","fc":[0.0549,0.0863,0.0941],"lh":69.6,"tr":0,"j":2,"ca":0},"t":0}]}},"ind":66},{"ty":5,"nm":"Loader Text 36","sr":1,"st":64,"op":66,"ip":64,"hd":false,"ddd":0,"bm":0,"hasMask":false,"ao":0,"ks":{"a":{"a":0,"k":[0,0,0],"ix":1},"s":{"a":0,"k":[100,100,100],"ix":6},"sk":{"a":0,"k":0},"p":{"a":0,"k":[85,50,0],"ix":2},"r":{"a":0,"k":0,"ix":10},"sa":{"a":0,"k":0},"o":{"a":1,"k":[{"o":{"x":0.167,"y":0.167},"i":{"x":0.833,"y":0.833},"s":[100],"t":261},{"s":[0],"t":268}],"ix":11}},"ef":[],"t":{"m":{"a":{"a":0,"k":[0,0],"ix":2},"g":1},"p":{},"a":[],"d":{"k":[{"s":{"f":"Montserrat-Bold","s":58,"t":"34%","fc":[0.0549,0.0863,0.0941],"lh":69.6,"tr":0,"j":2,"ca":0},"t":0}]}},"ind":67},{"ty":5,"nm":"Loader Text 35","sr":1,"st":63,"op":64,"ip":63,"hd":false,"ddd":0,"bm":0,"hasMask":false,"ao":0,"ks":{"a":{"a":0,"k":[0,0,0],"ix":1},"s":{"a":0,"k":[100,100,100],"ix":6},"sk":{"a":0,"k":0},"p":{"a":0,"k":[85,50,0],"ix":2},"r":{"a":0,"k":0,"ix":10},"sa":{"a":0,"k":0},"o":{"a":1,"k":[{"o":{"x":0.167,"y":0.167},"i":{"x":0.833,"y":0.833},"s":[100],"t":260},{"s":[0],"t":267}],"ix":11}},"ef":[],"t":{"m":{"a":{"a":0,"k":[0,0],"ix":2},"g":1},"p":{},"a":[],"d":{"k":[{"s":{"f":"Montserrat-Bold","s":58,"t":"33%","fc":[0.0549,0.0863,0.0941],"lh":69.6,"tr":0,"j":2,"ca":0},"t":0}]}},"ind":68},{"ty":5,"nm":"Loader Text 34","sr":1,"st":61,"op":63,"ip":61,"hd":false,"ddd":0,"bm":0,"hasMask":false,"ao":0,"ks":{"a":{"a":0,"k":[0,0,0],"ix":1},"s":{"a":0,"k":[100,100,100],"ix":6},"sk":{"a":0,"k":0},"p":{"a":0,"k":[85,50,0],"ix":2},"r":{"a":0,"k":0,"ix":10},"sa":{"a":0,"k":0},"o":{"a":1,"k":[{"o":{"x":0.167,"y":0.167},"i":{"x":0.833,"y":0.833},"s":[100],"t":258},{"s":[0],"t":265}],"ix":11}},"ef":[],"t":{"m":{"a":{"a":0,"k":[0,0],"ix":2},"g":1},"p":{},"a":[],"d":{"k":[{"s":{"f":"Montserrat-Bold","s":58,"t":"32%","fc":[0.0549,0.0863,0.0941],"lh":69.6,"tr":0,"j":2,"ca":0},"t":0}]}},"ind":69},{"ty":5,"nm":"Loader Text 33","sr":1,"st":59,"op":61,"ip":59,"hd":false,"ddd":0,"bm":0,"hasMask":false,"ao":0,"ks":{"a":{"a":0,"k":[0,0,0],"ix":1},"s":{"a":0,"k":[100,100,100],"ix":6},"sk":{"a":0,"k":0},"p":{"a":0,"k":[85,50,0],"ix":2},"r":{"a":0,"k":0,"ix":10},"sa":{"a":0,"k":0},"o":{"a":1,"k":[{"o":{"x":0.167,"y":0.167},"i":{"x":0.833,"y":0.833},"s":[100],"t":256},{"s":[0],"t":263}],"ix":11}},"ef":[],"t":{"m":{"a":{"a":0,"k":[0,0],"ix":2},"g":1},"p":{},"a":[],"d":{"k":[{"s":{"f":"Montserrat-Bold","s":58,"t":"31%","fc":[0.0549,0.0863,0.0941],"lh":69.6,"tr":0,"j":2,"ca":0},"t":0}]}},"ind":70},{"ty":5,"nm":"Loader Text 32","sr":1,"st":57,"op":59,"ip":57,"hd":false,"ddd":0,"bm":0,"hasMask":false,"ao":0,"ks":{"a":{"a":0,"k":[0,0,0],"ix":1},"s":{"a":0,"k":[100,100,100],"ix":6},"sk":{"a":0,"k":0},"p":{"a":0,"k":[85,50,0],"ix":2},"r":{"a":0,"k":0,"ix":10},"sa":{"a":0,"k":0},"o":{"a":1,"k":[{"o":{"x":0.167,"y":0.167},"i":{"x":0.833,"y":0.833},"s":[100],"t":254},{"s":[0],"t":261}],"ix":11}},"ef":[],"t":{"m":{"a":{"a":0,"k":[0,0],"ix":2},"g":1},"p":{},"a":[],"d":{"k":[{"s":{"f":"Montserrat-Bold","s":58,"t":"30%","fc":[0.0549,0.0863,0.0941],"lh":69.6,"tr":0,"j":2,"ca":0},"t":0}]}},"ind":71},{"ty":5,"nm":"Loader Text 31","sr":1,"st":55,"op":57,"ip":55,"hd":false,"ddd":0,"bm":0,"hasMask":false,"ao":0,"ks":{"a":{"a":0,"k":[0,0,0],"ix":1},"s":{"a":0,"k":[100,100,100],"ix":6},"sk":{"a":0,"k":0},"p":{"a":0,"k":[85,50,0],"ix":2},"r":{"a":0,"k":0,"ix":10},"sa":{"a":0,"k":0},"o":{"a":1,"k":[{"o":{"x":0.167,"y":0.167},"i":{"x":0.833,"y":0.833},"s":[100],"t":252},{"s":[0],"t":259}],"ix":11}},"ef":[],"t":{"m":{"a":{"a":0,"k":[0,0],"ix":2},"g":1},"p":{},"a":[],"d":{"k":[{"s":{"f":"Montserrat-Bold","s":58,"t":"29%","fc":[0.0549,0.0863,0.0941],"lh":69.6,"tr":0,"j":2,"ca":0},"t":0}]}},"ind":72},{"ty":5,"nm":"Loader Text 30","sr":1,"st":53,"op":55,"ip":53,"hd":false,"ddd":0,"bm":0,"hasMask":false,"ao":0,"ks":{"a":{"a":0,"k":[0,0,0],"ix":1},"s":{"a":0,"k":[100,100,100],"ix":6},"sk":{"a":0,"k":0},"p":{"a":0,"k":[85,50,0],"ix":2},"r":{"a":0,"k":0,"ix":10},"sa":{"a":0,"k":0},"o":{"a":1,"k":[{"o":{"x":0.167,"y":0.167},"i":{"x":0.833,"y":0.833},"s":[100],"t":250},{"s":[0],"t":257}],"ix":11}},"ef":[],"t":{"m":{"a":{"a":0,"k":[0,0],"ix":2},"g":1},"p":{},"a":[],"d":{"k":[{"s":{"f":"Montserrat-Bold","s":58,"t":"28%","fc":[0.0549,0.0863,0.0941],"lh":69.6,"tr":0,"j":2,"ca":0},"t":0}]}},"ind":73},{"ty":5,"nm":"Loader Text 29","sr":1,"st":51,"op":53,"ip":51,"hd":false,"ddd":0,"bm":0,"hasMask":false,"ao":0,"ks":{"a":{"a":0,"k":[0,0,0],"ix":1},"s":{"a":0,"k":[100,100,100],"ix":6},"sk":{"a":0,"k":0},"p":{"a":0,"k":[85,50,0],"ix":2},"r":{"a":0,"k":0,"ix":10},"sa":{"a":0,"k":0},"o":{"a":1,"k":[{"o":{"x":0.167,"y":0.167},"i":{"x":0.833,"y":0.833},"s":[100],"t":248},{"s":[0],"t":255}],"ix":11}},"ef":[],"t":{"m":{"a":{"a":0,"k":[0,0],"ix":2},"g":1},"p":{},"a":[],"d":{"k":[{"s":{"f":"Montserrat-Bold","s":58,"t":"27%","fc":[0.0549,0.0863,0.0941],"lh":69.6,"tr":0,"j":2,"ca":0},"t":0}]}},"ind":74},{"ty":5,"nm":"Loader Text 28","sr":1,"st":49,"op":51,"ip":49,"hd":false,"ddd":0,"bm":0,"hasMask":false,"ao":0,"ks":{"a":{"a":0,"k":[0,0,0],"ix":1},"s":{"a":0,"k":[100,100,100],"ix":6},"sk":{"a":0,"k":0},"p":{"a":0,"k":[85,50,0],"ix":2},"r":{"a":0,"k":0,"ix":10},"sa":{"a":0,"k":0},"o":{"a":1,"k":[{"o":{"x":0.167,"y":0.167},"i":{"x":0.833,"y":0.833},"s":[100],"t":246},{"s":[0],"t":253}],"ix":11}},"ef":[],"t":{"m":{"a":{"a":0,"k":[0,0],"ix":2},"g":1},"p":{},"a":[],"d":{"k":[{"s":{"f":"Montserrat-Bold","s":58,"t":"26%","fc":[0.0549,0.0863,0.0941],"lh":69.6,"tr":0,"j":2,"ca":0},"t":0}]}},"ind":75},{"ty":5,"nm":"Loader Text 27","sr":1,"st":47,"op":49,"ip":47,"hd":false,"ddd":0,"bm":0,"hasMask":false,"ao":0,"ks":{"a":{"a":0,"k":[0,0,0],"ix":1},"s":{"a":0,"k":[100,100,100],"ix":6},"sk":{"a":0,"k":0},"p":{"a":0,"k":[85,50,0],"ix":2},"r":{"a":0,"k":0,"ix":10},"sa":{"a":0,"k":0},"o":{"a":1,"k":[{"o":{"x":0.167,"y":0.167},"i":{"x":0.833,"y":0.833},"s":[100],"t":244},{"s":[0],"t":251}],"ix":11}},"ef":[],"t":{"m":{"a":{"a":0,"k":[0,0],"ix":2},"g":1},"p":{},"a":[],"d":{"k":[{"s":{"f":"Montserrat-Bold","s":58,"t":"25%","fc":[0.0549,0.0863,0.0941],"lh":69.6,"tr":0,"j":2,"ca":0},"t":0}]}},"ind":76},{"ty":5,"nm":"Loader Text 26","sr":1,"st":45,"op":47,"ip":45,"hd":false,"ddd":0,"bm":0,"hasMask":false,"ao":0,"ks":{"a":{"a":0,"k":[0,0,0],"ix":1},"s":{"a":0,"k":[100,100,100],"ix":6},"sk":{"a":0,"k":0},"p":{"a":0,"k":[85,50,0],"ix":2},"r":{"a":0,"k":0,"ix":10},"sa":{"a":0,"k":0},"o":{"a":1,"k":[{"o":{"x":0.167,"y":0.167},"i":{"x":0.833,"y":0.833},"s":[100],"t":242},{"s":[0],"t":249}],"ix":11}},"ef":[],"t":{"m":{"a":{"a":0,"k":[0,0],"ix":2},"g":1},"p":{},"a":[],"d":{"k":[{"s":{"f":"Montserrat-Bold","s":58,"t":"24%","fc":[0.0549,0.0863,0.0941],"lh":69.6,"tr":0,"j":2,"ca":0},"t":0}]}},"ind":77},{"ty":5,"nm":"Loader Text 25","sr":1,"st":43,"op":45,"ip":43,"hd":false,"ddd":0,"bm":0,"hasMask":false,"ao":0,"ks":{"a":{"a":0,"k":[0,0,0],"ix":1},"s":{"a":0,"k":[100,100,100],"ix":6},"sk":{"a":0,"k":0},"p":{"a":0,"k":[85,50,0],"ix":2},"r":{"a":0,"k":0,"ix":10},"sa":{"a":0,"k":0},"o":{"a":1,"k":[{"o":{"x":0.167,"y":0.167},"i":{"x":0.833,"y":0.833},"s":[100],"t":240},{"s":[0],"t":247}],"ix":11}},"ef":[],"t":{"m":{"a":{"a":0,"k":[0,0],"ix":2},"g":1},"p":{},"a":[],"d":{"k":[{"s":{"f":"Montserrat-Bold","s":58,"t":"23%","fc":[0.0549,0.0863,0.0941],"lh":69.6,"tr":0,"j":2,"ca":0},"t":0}]}},"ind":78},{"ty":5,"nm":"Loader Text 24","sr":1,"st":42,"op":43,"ip":42,"hd":false,"ddd":0,"bm":0,"hasMask":false,"ao":0,"ks":{"a":{"a":0,"k":[0,0,0],"ix":1},"s":{"a":0,"k":[100,100,100],"ix":6},"sk":{"a":0,"k":0},"p":{"a":0,"k":[85,50,0],"ix":2},"r":{"a":0,"k":0,"ix":10},"sa":{"a":0,"k":0},"o":{"a":1,"k":[{"o":{"x":0.167,"y":0.167},"i":{"x":0.833,"y":0.833},"s":[100],"t":239},{"s":[0],"t":246}],"ix":11}},"ef":[],"t":{"m":{"a":{"a":0,"k":[0,0],"ix":2},"g":1},"p":{},"a":[],"d":{"k":[{"s":{"f":"Montserrat-Bold","s":58,"t":"22%","fc":[0.0549,0.0863,0.0941],"lh":69.6,"tr":0,"j":2,"ca":0},"t":0}]}},"ind":79},{"ty":5,"nm":"Loader Text 23","sr":1,"st":40,"op":42,"ip":40,"hd":false,"ddd":0,"bm":0,"hasMask":false,"ao":0,"ks":{"a":{"a":0,"k":[0,0,0],"ix":1},"s":{"a":0,"k":[100,100,100],"ix":6},"sk":{"a":0,"k":0},"p":{"a":0,"k":[85,50,0],"ix":2},"r":{"a":0,"k":0,"ix":10},"sa":{"a":0,"k":0},"o":{"a":1,"k":[{"o":{"x":0.167,"y":0.167},"i":{"x":0.833,"y":0.833},"s":[100],"t":237},{"s":[0],"t":244}],"ix":11}},"ef":[],"t":{"m":{"a":{"a":0,"k":[0,0],"ix":2},"g":1},"p":{},"a":[],"d":{"k":[{"s":{"f":"Montserrat-Bold","s":58,"t":"21%","fc":[0.0549,0.0863,0.0941],"lh":69.6,"tr":0,"j":2,"ca":0},"t":0}]}},"ind":80},{"ty":5,"nm":"Loader Text 22","sr":1,"st":38,"op":40,"ip":38,"hd":false,"ddd":0,"bm":0,"hasMask":false,"ao":0,"ks":{"a":{"a":0,"k":[0,0,0],"ix":1},"s":{"a":0,"k":[100,100,100],"ix":6},"sk":{"a":0,"k":0},"p":{"a":0,"k":[85,50,0],"ix":2},"r":{"a":0,"k":0,"ix":10},"sa":{"a":0,"k":0},"o":{"a":1,"k":[{"o":{"x":0.167,"y":0.167},"i":{"x":0.833,"y":0.833},"s":[100],"t":235},{"s":[0],"t":242}],"ix":11}},"ef":[],"t":{"m":{"a":{"a":0,"k":[0,0],"ix":2},"g":1},"p":{},"a":[],"d":{"k":[{"s":{"f":"Montserrat-Bold","s":58,"t":"20%","fc":[0.0549,0.0863,0.0941],"lh":69.6,"tr":0,"j":2,"ca":0},"t":0}]}},"ind":81},{"ty":5,"nm":"Loader Text 21","sr":1,"st":36,"op":38,"ip":36,"hd":false,"ddd":0,"bm":0,"hasMask":false,"ao":0,"ks":{"a":{"a":0,"k":[0,0,0],"ix":1},"s":{"a":0,"k":[100,100,100],"ix":6},"sk":{"a":0,"k":0},"p":{"a":0,"k":[85,50,0],"ix":2},"r":{"a":0,"k":0,"ix":10},"sa":{"a":0,"k":0},"o":{"a":1,"k":[{"o":{"x":0.167,"y":0.167},"i":{"x":0.833,"y":0.833},"s":[100],"t":233},{"s":[0],"t":240}],"ix":11}},"ef":[],"t":{"m":{"a":{"a":0,"k":[0,0],"ix":2},"g":1},"p":{},"a":[],"d":{"k":[{"s":{"f":"Montserrat-Bold","s":58,"t":"19%","fc":[0.0549,0.0863,0.0941],"lh":69.6,"tr":0,"j":2,"ca":0},"t":0}]}},"ind":82},{"ty":5,"nm":"Loader Text 20","sr":1,"st":34,"op":36,"ip":34,"hd":false,"ddd":0,"bm":0,"hasMask":false,"ao":0,"ks":{"a":{"a":0,"k":[0,0,0],"ix":1},"s":{"a":0,"k":[100,100,100],"ix":6},"sk":{"a":0,"k":0},"p":{"a":0,"k":[85,50,0],"ix":2},"r":{"a":0,"k":0,"ix":10},"sa":{"a":0,"k":0},"o":{"a":1,"k":[{"o":{"x":0.167,"y":0.167},"i":{"x":0.833,"y":0.833},"s":[100],"t":231},{"s":[0],"t":238}],"ix":11}},"ef":[],"t":{"m":{"a":{"a":0,"k":[0,0],"ix":2},"g":1},"p":{},"a":[],"d":{"k":[{"s":{"f":"Montserrat-Bold","s":58,"t":"18%","fc":[0.0549,0.0863,0.0941],"lh":69.6,"tr":0,"j":2,"ca":0},"t":0}]}},"ind":83},{"ty":5,"nm":"Loader Text 19","sr":1,"st":32,"op":34,"ip":32,"hd":false,"ddd":0,"bm":0,"hasMask":false,"ao":0,"ks":{"a":{"a":0,"k":[0,0,0],"ix":1},"s":{"a":0,"k":[100,100,100],"ix":6},"sk":{"a":0,"k":0},"p":{"a":0,"k":[85,50,0],"ix":2},"r":{"a":0,"k":0,"ix":10},"sa":{"a":0,"k":0},"o":{"a":1,"k":[{"o":{"x":0.167,"y":0.167},"i":{"x":0.833,"y":0.833},"s":[100],"t":229},{"s":[0],"t":236}],"ix":11}},"ef":[],"t":{"m":{"a":{"a":0,"k":[0,0],"ix":2},"g":1},"p":{},"a":[],"d":{"k":[{"s":{"f":"Montserrat-Bold","s":58,"t":"17%","fc":[0.0549,0.0863,0.0941],"lh":69.6,"tr":0,"j":2,"ca":0},"t":0}]}},"ind":84},{"ty":5,"nm":"Loader Text 18","sr":1,"st":30,"op":32,"ip":30,"hd":false,"ddd":0,"bm":0,"hasMask":false,"ao":0,"ks":{"a":{"a":0,"k":[0,0,0],"ix":1},"s":{"a":0,"k":[100,100,100],"ix":6},"sk":{"a":0,"k":0},"p":{"a":0,"k":[85,50,0],"ix":2},"r":{"a":0,"k":0,"ix":10},"sa":{"a":0,"k":0},"o":{"a":1,"k":[{"o":{"x":0.167,"y":0.167},"i":{"x":0.833,"y":0.833},"s":[100],"t":227},{"s":[0],"t":234}],"ix":11}},"ef":[],"t":{"m":{"a":{"a":0,"k":[0,0],"ix":2},"g":1},"p":{},"a":[],"d":{"k":[{"s":{"f":"Montserrat-Bold","s":58,"t":"16%","fc":[0.0549,0.0863,0.0941],"lh":69.6,"tr":0,"j":2,"ca":0},"t":0}]}},"ind":85},{"ty":5,"nm":"Loader Text 17","sr":1,"st":28,"op":30,"ip":28,"hd":false,"ddd":0,"bm":0,"hasMask":false,"ao":0,"ks":{"a":{"a":0,"k":[0,0,0],"ix":1},"s":{"a":0,"k":[100,100,100],"ix":6},"sk":{"a":0,"k":0},"p":{"a":0,"k":[85,50,0],"ix":2},"r":{"a":0,"k":0,"ix":10},"sa":{"a":0,"k":0},"o":{"a":1,"k":[{"o":{"x":0.167,"y":0.167},"i":{"x":0.833,"y":0.833},"s":[100],"t":225},{"s":[0],"t":232}],"ix":11}},"ef":[],"t":{"m":{"a":{"a":0,"k":[0,0],"ix":2},"g":1},"p":{},"a":[],"d":{"k":[{"s":{"f":"Montserrat-Bold","s":58,"t":"15%","fc":[0.0549,0.0863,0.0941],"lh":69.6,"tr":0,"j":2,"ca":0},"t":0}]}},"ind":86},{"ty":5,"nm":"Loader Text 16","sr":1,"st":26,"op":28,"ip":26,"hd":false,"ddd":0,"bm":0,"hasMask":false,"ao":0,"ks":{"a":{"a":0,"k":[0,0,0],"ix":1},"s":{"a":0,"k":[100,100,100],"ix":6},"sk":{"a":0,"k":0},"p":{"a":0,"k":[85,50,0],"ix":2},"r":{"a":0,"k":0,"ix":10},"sa":{"a":0,"k":0},"o":{"a":1,"k":[{"o":{"x":0.167,"y":0.167},"i":{"x":0.833,"y":0.833},"s":[100],"t":223},{"s":[0],"t":230}],"ix":11}},"ef":[],"t":{"m":{"a":{"a":0,"k":[0,0],"ix":2},"g":1},"p":{},"a":[],"d":{"k":[{"s":{"f":"Montserrat-Bold","s":58,"t":"14%","fc":[0.0549,0.0863,0.0941],"lh":69.6,"tr":0,"j":2,"ca":0},"t":0}]}},"ind":87},{"ty":5,"nm":"Loader Text 15","sr":1,"st":24,"op":26,"ip":24,"hd":false,"ddd":0,"bm":0,"hasMask":false,"ao":0,"ks":{"a":{"a":0,"k":[0,0,0],"ix":1},"s":{"a":0,"k":[100,100,100],"ix":6},"sk":{"a":0,"k":0},"p":{"a":0,"k":[85,50,0],"ix":2},"r":{"a":0,"k":0,"ix":10},"sa":{"a":0,"k":0},"o":{"a":1,"k":[{"o":{"x":0.167,"y":0.167},"i":{"x":0.833,"y":0.833},"s":[100],"t":221},{"s":[0],"t":228}],"ix":11}},"ef":[],"t":{"m":{"a":{"a":0,"k":[0,0],"ix":2},"g":1},"p":{},"a":[],"d":{"k":[{"s":{"f":"Montserrat-Bold","s":58,"t":"13%","fc":[0.0549,0.0863,0.0941],"lh":69.6,"tr":0,"j":2,"ca":0},"t":0}]}},"ind":88},{"ty":5,"nm":"Loader Text 14","sr":1,"st":22,"op":24,"ip":22,"hd":false,"ddd":0,"bm":0,"hasMask":false,"ao":0,"ks":{"a":{"a":0,"k":[0,0,0],"ix":1},"s":{"a":0,"k":[100,100,100],"ix":6},"sk":{"a":0,"k":0},"p":{"a":0,"k":[85,50,0],"ix":2},"r":{"a":0,"k":0,"ix":10},"sa":{"a":0,"k":0},"o":{"a":1,"k":[{"o":{"x":0.167,"y":0.167},"i":{"x":0.833,"y":0.833},"s":[100],"t":219},{"s":[0],"t":226}],"ix":11}},"ef":[],"t":{"m":{"a":{"a":0,"k":[0,0],"ix":2},"g":1},"p":{},"a":[],"d":{"k":[{"s":{"f":"Montserrat-Bold","s":58,"t":"12%","fc":[0.0549,0.0863,0.0941],"lh":69.6,"tr":0,"j":2,"ca":0},"t":0}]}},"ind":89},{"ty":5,"nm":"Loader Text 13","sr":1,"st":21,"op":22,"ip":21,"hd":false,"ddd":0,"bm":0,"hasMask":false,"ao":0,"ks":{"a":{"a":0,"k":[0,0,0],"ix":1},"s":{"a":0,"k":[100,100,100],"ix":6},"sk":{"a":0,"k":0},"p":{"a":0,"k":[85,50,0],"ix":2},"r":{"a":0,"k":0,"ix":10},"sa":{"a":0,"k":0},"o":{"a":1,"k":[{"o":{"x":0.167,"y":0.167},"i":{"x":0.833,"y":0.833},"s":[100],"t":218},{"s":[0],"t":225}],"ix":11}},"ef":[],"t":{"m":{"a":{"a":0,"k":[0,0],"ix":2},"g":1},"p":{},"a":[],"d":{"k":[{"s":{"f":"Montserrat-Bold","s":58,"t":"11%","fc":[0.0549,0.0863,0.0941],"lh":69.6,"tr":0,"j":2,"ca":0},"t":0}]}},"ind":90},{"ty":5,"nm":"Loader Text 12","sr":1,"st":19,"op":21,"ip":19,"hd":false,"ddd":0,"bm":0,"hasMask":false,"ao":0,"ks":{"a":{"a":0,"k":[0,0,0],"ix":1},"s":{"a":0,"k":[100,100,100],"ix":6},"sk":{"a":0,"k":0},"p":{"a":0,"k":[85,50,0],"ix":2},"r":{"a":0,"k":0,"ix":10},"sa":{"a":0,"k":0},"o":{"a":1,"k":[{"o":{"x":0.167,"y":0.167},"i":{"x":0.833,"y":0.833},"s":[100],"t":216},{"s":[0],"t":223}],"ix":11}},"ef":[],"t":{"m":{"a":{"a":0,"k":[0,0],"ix":2},"g":1},"p":{},"a":[],"d":{"k":[{"s":{"f":"Montserrat-Bold","s":58,"t":"10%","fc":[0.0549,0.0863,0.0941],"lh":69.6,"tr":0,"j":2,"ca":0},"t":0}]}},"ind":91},{"ty":5,"nm":"Loader Text 11","sr":1,"st":17,"op":19,"ip":17,"hd":false,"ddd":0,"bm":0,"hasMask":false,"ao":0,"ks":{"a":{"a":0,"k":[0,0,0],"ix":1},"s":{"a":0,"k":[100,100,100],"ix":6},"sk":{"a":0,"k":0},"p":{"a":0,"k":[85,50,0],"ix":2},"r":{"a":0,"k":0,"ix":10},"sa":{"a":0,"k":0},"o":{"a":1,"k":[{"o":{"x":0.167,"y":0.167},"i":{"x":0.833,"y":0.833},"s":[100],"t":214},{"s":[0],"t":221}],"ix":11}},"ef":[],"t":{"m":{"a":{"a":0,"k":[0,0],"ix":2},"g":1},"p":{},"a":[],"d":{"k":[{"s":{"f":"Montserrat-Bold","s":58,"t":"9%","fc":[0.0549,0.0863,0.0941],"lh":69.6,"tr":0,"j":2,"ca":0},"t":0}]}},"ind":92},{"ty":5,"nm":"Loader Text 10","sr":1,"st":15,"op":17,"ip":15,"hd":false,"ddd":0,"bm":0,"hasMask":false,"ao":0,"ks":{"a":{"a":0,"k":[0,0,0],"ix":1},"s":{"a":0,"k":[100,100,100],"ix":6},"sk":{"a":0,"k":0},"p":{"a":0,"k":[85,50,0],"ix":2},"r":{"a":0,"k":0,"ix":10},"sa":{"a":0,"k":0},"o":{"a":1,"k":[{"o":{"x":0.167,"y":0.167},"i":{"x":0.833,"y":0.833},"s":[100],"t":212},{"s":[0],"t":219}],"ix":11}},"ef":[],"t":{"m":{"a":{"a":0,"k":[0,0],"ix":2},"g":1},"p":{},"a":[],"d":{"k":[{"s":{"f":"Montserrat-Bold","s":58,"t":"8%","fc":[0.0549,0.0863,0.0941],"lh":69.6,"tr":0,"j":2,"ca":0},"t":0}]}},"ind":93},{"ty":5,"nm":"Loader Text 9","sr":1,"st":13,"op":15,"ip":13,"hd":false,"ddd":0,"bm":0,"hasMask":false,"ao":0,"ks":{"a":{"a":0,"k":[0,0,0],"ix":1},"s":{"a":0,"k":[100,100,100],"ix":6},"sk":{"a":0,"k":0},"p":{"a":0,"k":[85,50,0],"ix":2},"r":{"a":0,"k":0,"ix":10},"sa":{"a":0,"k":0},"o":{"a":1,"k":[{"o":{"x":0.167,"y":0.167},"i":{"x":0.833,"y":0.833},"s":[100],"t":210},{"s":[0],"t":217}],"ix":11}},"ef":[],"t":{"m":{"a":{"a":0,"k":[0,0],"ix":2},"g":1},"p":{},"a":[],"d":{"k":[{"s":{"f":"Montserrat-Bold","s":58,"t":"7%","fc":[0.0549,0.0863,0.0941],"lh":69.6,"tr":0,"j":2,"ca":0},"t":0}]}},"ind":94},{"ty":5,"nm":"Loader Text 8","sr":1,"st":11,"op":13,"ip":11,"hd":false,"ddd":0,"bm":0,"hasMask":false,"ao":0,"ks":{"a":{"a":0,"k":[0,0,0],"ix":1},"s":{"a":0,"k":[100,100,100],"ix":6},"sk":{"a":0,"k":0},"p":{"a":0,"k":[85,50,0],"ix":2},"r":{"a":0,"k":0,"ix":10},"sa":{"a":0,"k":0},"o":{"a":1,"k":[{"o":{"x":0.167,"y":0.167},"i":{"x":0.833,"y":0.833},"s":[100],"t":208},{"s":[0],"t":215}],"ix":11}},"ef":[],"t":{"m":{"a":{"a":0,"k":[0,0],"ix":2},"g":1},"p":{},"a":[],"d":{"k":[{"s":{"f":"Montserrat-Bold","s":58,"t":"6%","fc":[0.0549,0.0863,0.0941],"lh":69.6,"tr":0,"j":2,"ca":0},"t":0}]}},"ind":95},{"ty":5,"nm":"Loader Text 7","sr":1,"st":8,"op":11,"ip":8,"hd":false,"ddd":0,"bm":0,"hasMask":false,"ao":0,"ks":{"a":{"a":0,"k":[0,0,0],"ix":1},"s":{"a":0,"k":[100,100,100],"ix":6},"sk":{"a":0,"k":0},"p":{"a":0,"k":[85,50,0],"ix":2},"r":{"a":0,"k":0,"ix":10},"sa":{"a":0,"k":0},"o":{"a":1,"k":[{"o":{"x":0.167,"y":0.167},"i":{"x":0.833,"y":0.833},"s":[100],"t":205},{"s":[0],"t":212}],"ix":11}},"ef":[],"t":{"m":{"a":{"a":0,"k":[0,0],"ix":2},"g":1},"p":{},"a":[],"d":{"k":[{"s":{"f":"Montserrat-Bold","s":58,"t":"5%","fc":[0.0549,0.0863,0.0941],"lh":69.6,"tr":0,"j":2,"ca":0},"t":0}]}},"ind":96},{"ty":5,"nm":"Loader Text 6","sr":1,"st":6,"op":8,"ip":6,"hd":false,"ddd":0,"bm":0,"hasMask":false,"ao":0,"ks":{"a":{"a":0,"k":[0,0,0],"ix":1},"s":{"a":0,"k":[100,100,100],"ix":6},"sk":{"a":0,"k":0},"p":{"a":0,"k":[85,50,0],"ix":2},"r":{"a":0,"k":0,"ix":10},"sa":{"a":0,"k":0},"o":{"a":1,"k":[{"o":{"x":0.167,"y":0.167},"i":{"x":0.833,"y":0.833},"s":[100],"t":203},{"s":[0],"t":210}],"ix":11}},"ef":[],"t":{"m":{"a":{"a":0,"k":[0,0],"ix":2},"g":1},"p":{},"a":[],"d":{"k":[{"s":{"f":"Montserrat-Bold","s":58,"t":"4%","fc":[0.0549,0.0863,0.0941],"lh":69.6,"tr":0,"j":2,"ca":0},"t":0}]}},"ind":97},{"ty":5,"nm":"Loader Text 5","sr":1,"st":5,"op":6,"ip":5,"hd":false,"ddd":0,"bm":0,"hasMask":false,"ao":0,"ks":{"a":{"a":0,"k":[0,0,0],"ix":1},"s":{"a":0,"k":[100,100,100],"ix":6},"sk":{"a":0,"k":0},"p":{"a":0,"k":[85,50,0],"ix":2},"r":{"a":0,"k":0,"ix":10},"sa":{"a":0,"k":0},"o":{"a":1,"k":[{"o":{"x":0.167,"y":0.167},"i":{"x":0.833,"y":0.833},"s":[100],"t":202},{"s":[0],"t":209}],"ix":11}},"ef":[],"t":{"m":{"a":{"a":0,"k":[0,0],"ix":2},"g":1},"p":{},"a":[],"d":{"k":[{"s":{"f":"Montserrat-Bold","s":58,"t":"3%","fc":[0.0549,0.0863,0.0941],"lh":69.6,"tr":0,"j":2,"ca":0},"t":0}]}},"ind":98},{"ty":5,"nm":"Loader Text 4","sr":1,"st":4,"op":5,"ip":4,"hd":false,"ddd":0,"bm":0,"hasMask":false,"ao":0,"ks":{"a":{"a":0,"k":[0,0,0],"ix":1},"s":{"a":0,"k":[100,100,100],"ix":6},"sk":{"a":0,"k":0},"p":{"a":0,"k":[85,50,0],"ix":2},"r":{"a":0,"k":0,"ix":10},"sa":{"a":0,"k":0},"o":{"a":1,"k":[{"o":{"x":0.167,"y":0.167},"i":{"x":0.833,"y":0.833},"s":[100],"t":201},{"s":[0],"t":208}],"ix":11}},"ef":[],"t":{"m":{"a":{"a":0,"k":[0,0],"ix":2},"g":1},"p":{},"a":[],"d":{"k":[{"s":{"f":"Montserrat-Bold","s":58,"t":"2%","fc":[0.0549,0.0863,0.0941],"lh":69.6,"tr":0,"j":2,"ca":0},"t":0}]}},"ind":99},{"ty":5,"nm":"Loader Text 3","sr":1,"st":1,"op":4,"ip":1,"hd":false,"ddd":0,"bm":0,"hasMask":false,"ao":0,"ks":{"a":{"a":0,"k":[0,0,0],"ix":1},"s":{"a":0,"k":[100,100,100],"ix":6},"sk":{"a":0,"k":0},"p":{"a":0,"k":[85,50,0],"ix":2},"r":{"a":0,"k":0,"ix":10},"sa":{"a":0,"k":0},"o":{"a":1,"k":[{"o":{"x":0.167,"y":0.167},"i":{"x":0.833,"y":0.833},"s":[100],"t":198},{"s":[0],"t":205}],"ix":11}},"ef":[],"t":{"m":{"a":{"a":0,"k":[0,0],"ix":2},"g":1},"p":{},"a":[],"d":{"k":[{"s":{"f":"Montserrat-Bold","s":58,"t":"1%","fc":[0.0549,0.0863,0.0941],"lh":69.6,"tr":0,"j":2,"ca":0},"t":0}]}},"ind":100},{"ty":5,"nm":"Loader Text 2","sr":1,"st":0,"op":1,"ip":0,"hd":false,"ddd":0,"bm":0,"hasMask":false,"ao":0,"ks":{"a":{"a":0,"k":[0,0,0],"ix":1},"s":{"a":0,"k":[100,100,100],"ix":6},"sk":{"a":0,"k":0},"p":{"a":0,"k":[85,50,0],"ix":2},"r":{"a":0,"k":0,"ix":10},"sa":{"a":0,"k":0},"o":{"a":1,"k":[{"o":{"x":0.167,"y":0.167},"i":{"x":0.833,"y":0.833},"s":[100],"t":197},{"s":[0],"t":204}],"ix":11}},"ef":[],"t":{"m":{"a":{"a":0,"k":[0,0],"ix":2},"g":1},"p":{},"a":[],"d":{"k":[{"s":{"f":"Montserrat-Bold","s":58,"t":"0%","fc":[0.0549,0.0863,0.0941],"lh":69.6,"tr":0,"j":2,"ca":0},"t":0}]}},"ind":101}]}]}